{
	"Index":2203,
	"Name":"12n114",
	"Hyperbolic":true,
	"Torus":false,
	"Satellite":false,
	"Diagrams":[
		{
			"Scode":"{6, 24, -11, 2, 18, -5, 20, 22, 8, 12, 14, 16}",
			"Acode":"{4, 1, -7, 2, 10, -4, 11, 12, 5, 7, 8, 9}",
			"PDcode":[
				"{1, 7, 2, 6}",
				"{3, 1, 4, 24}",
				"{4, 11, 5, 12}",
				"{7, 3, 8, 2}",
				"{9, 19, 10, 18}",
				"{10, 5, 11, 6}",
				"{13, 21, 14, 20}",
				"{15, 23, 16, 22}",
				"{17, 9, 18, 8}",
				"{19, 13, 20, 12}",
				"{21, 15, 22, 14}",
				"{23, 17, 24, 16}"
			],
			"SolvingSeqs":[
				[
					"{4, 8, 12}",
					[],
					[
						"{8, 12, 9, 1}",
						"{12, 9, 1, 1}",
						"{12, 8, 11, 2}",
						"{8, 11, 7, 2}",
						"{4, -7, 3, 2}",
						"{3, 1, 2, 2}",
						"{7, -4, 6, 2}",
						"{11, 7, 10, 2}",
						"{6, 10, 5, 2}"
					],
					"{1, 4}",
					"{9}",
					9
				]
			],
			"GeometricRepresentation":{
				"Volume":12.554072587073858254866461261345759481417678086789335056413781110709261610778375180508444257768944276887086,
				"ChernSimons":-9.573958433086483325796491886837808879988879417529748254943036695345250288441503696264820612011991657846513
			}
		}
	],
	"ParabolicReps":[
		{
			"DiagramIdx":1,
			"SolvingSeqIdx":1,
			"u":{
				"CheckEq":[
					"-1 + a - b - a^2*u*(a^2*b*u + a*(u - a*b*u)) - (u - a*b*u)*(a^2*b*u + a*(u - a*b*u)) - a^2*u*(u + a*u*(b - a*u^2)) + (a - a^2*u*(a^2*b*u + a*(u - a*b*u)))*(-((u + a*u*(b - a*u^2))^2*(a - a^2*u*(a^2*b*u + a*(u - a*b*u)))) + (b + (u - a*b*u)*(a^2*b*u + a*(u - a*b*u)))*(1 + a^2*u*(u + a*u*(b - a*u^2))))",
					"b + (u - a*b*u)*(a^2*b*u + a*(u - a*b*u)) - (u + a*u*(b - a*u^2))^2 + (b + (u - a*b*u)*(a^2*b*u + a*(u - a*b*u)))*(-((u + a*u*(b - a*u^2))^2*(a - a^2*u*(a^2*b*u + a*(u - a*b*u)))) + (b + (u - a*b*u)*(a^2*b*u + a*(u - a*b*u)))*(1 + a^2*u*(u + a*u*(b - a*u^2))))",
					"1 + u - a^2*u + a*u*(b - a*u^2) + (a - a^2*u*(-(a^2*u*(b - a*u^2)) + a*(u + a*u*(b - a*u^2))))*(-((u + a*u*(b - a*u^2))*(a - a^2*u*(-(a^2*u*(b - a*u^2)) + a*(u + a*u*(b - a*u^2))))) + (-u + a^2*u - a*u*(b - a*u^2))*(b - a*u^2 - (u + a*u*(b - a*u^2))*(-(a^2*u*(b - a*u^2)) + a*(u + a*u*(b - a*u^2))))) + (1 + a^2*u*(u + a*u*(b - a*u^2)) - (a - a^2*u*(a^2*b*u + a*(u - a*b*u)))*(-((u + a*u*(b - a*u^2))^2*(a - a^2*u*(a^2*b*u + a*(u - a*b*u)))) + (b + (u - a*b*u)*(a^2*b*u + a*(u - a*b*u)))*(1 + a^2*u*(u + a*u*(b - a*u^2)))))*((u + a*u*(b - a*u^2))^2 - (b + (u - a*b*u)*(a^2*b*u + a*(u - a*b*u)))*(-((u + a*u*(b - a*u^2))^2*(a - a^2*u*(a^2*b*u + a*(u - a*b*u)))) + (b + (u - a*b*u)*(a^2*b*u + a*(u - a*b*u)))*(1 + a^2*u*(u + a*u*(b - a*u^2)))))",
					"-u - a*u*(b - a*u^2) + (b - a*u^2 - (u + a*u*(b - a*u^2))*(-(a^2*u*(b - a*u^2)) + a*(u + a*u*(b - a*u^2))))*(-((u + a*u*(b - a*u^2))*(a - a^2*u*(-(a^2*u*(b - a*u^2)) + a*(u + a*u*(b - a*u^2))))) + (-u + a^2*u - a*u*(b - a*u^2))*(b - a*u^2 - (u + a*u*(b - a*u^2))*(-(a^2*u*(b - a*u^2)) + a*(u + a*u*(b - a*u^2))))) + ((u + a*u*(b - a*u^2))^2 - (b + (u - a*b*u)*(a^2*b*u + a*(u - a*b*u)))*(-((u + a*u*(b - a*u^2))^2*(a - a^2*u*(a^2*b*u + a*(u - a*b*u)))) + (b + (u - a*b*u)*(a^2*b*u + a*(u - a*b*u)))*(1 + a^2*u*(u + a*u*(b - a*u^2)))))^2"
				],
				"TimingForPrimaryIdeals":0.199349
			},
			"v":{
				"CheckEq":[
					"b - b^4*v^2 + b^2*v*(a*b^2*v - b*(v + a*b*v)) + (b + b^2*v*(a*b^2*v - b*(v + a*b*v)))*(-(b^4*v^2*(a + (v + a*b*v)*(a*b^2*v - b*(v + a*b*v)))) + (b + b^2*v*(a*b^2*v - b*(v + a*b*v)))*(1 - b^2*v*(v - b*v*(a + b*v^2))))",
					"-1 + a - b - b^2*v*(a*b^2*v - b*(v + a*b*v)) + (v + a*b*v)*(a*b^2*v - b*(v + a*b*v)) + b^2*v*(v - b*v*(a + b*v^2)) + (a + (v + a*b*v)*(a*b^2*v - b*(v + a*b*v)))*(-(b^4*v^2*(a + (v + a*b*v)*(a*b^2*v - b*(v + a*b*v)))) + (b + b^2*v*(a*b^2*v - b*(v + a*b*v)))*(1 - b^2*v*(v - b*v*(a + b*v^2))))",
					"b^2*v + (b + b^2*v*(-(b^2*v*(a + b*v^2)) - b*(v - b*v*(a + b*v^2))))*((v + b^2*v - b*v*(a + b*v^2))*(b + b^2*v*(-(b^2*v*(a + b*v^2)) - b*(v - b*v*(a + b*v^2)))) + b^2*v*(a + b*v^2 - (v - b*v*(a + b*v^2))*(-(b^2*v*(a + b*v^2)) - b*(v - b*v*(a + b*v^2))))) + (b^4*v^2 - (b + b^2*v*(a*b^2*v - b*(v + a*b*v)))*(-(b^4*v^2*(a + (v + a*b*v)*(a*b^2*v - b*(v + a*b*v)))) + (b + b^2*v*(a*b^2*v - b*(v + a*b*v)))*(1 - b^2*v*(v - b*v*(a + b*v^2)))))^2",
					"1 - v - b^2*v + b*v*(a + b*v^2) + (a + b*v^2 - (v - b*v*(a + b*v^2))*(-(b^2*v*(a + b*v^2)) - b*(v - b*v*(a + b*v^2))))*((v + b^2*v - b*v*(a + b*v^2))*(b + b^2*v*(-(b^2*v*(a + b*v^2)) - b*(v - b*v*(a + b*v^2)))) + b^2*v*(a + b*v^2 - (v - b*v*(a + b*v^2))*(-(b^2*v*(a + b*v^2)) - b*(v - b*v*(a + b*v^2))))) + (b^4*v^2 - (b + b^2*v*(a*b^2*v - b*(v + a*b*v)))*(-(b^4*v^2*(a + (v + a*b*v)*(a*b^2*v - b*(v + a*b*v)))) + (b + b^2*v*(a*b^2*v - b*(v + a*b*v)))*(1 - b^2*v*(v - b*v*(a + b*v^2)))))*(1 - b^2*v*(v - b*v*(a + b*v^2)) - (a + (v + a*b*v)*(a*b^2*v - b*(v + a*b*v)))*(-(b^4*v^2*(a + (v + a*b*v)*(a*b^2*v - b*(v + a*b*v)))) + (b + b^2*v*(a*b^2*v - b*(v + a*b*v)))*(1 - b^2*v*(v - b*v*(a + b*v^2)))))"
				],
				"TimingForPrimaryIdeals":3.7013e-2
			},
			"PrimaryIdeals":[
				{
					"IdealName":"J12n114_0",
					"Generators":[
						"-31 + 106*u + 476*u^2 - 1976*u^3 - 127*u^4 - 2926*u^5 + 34000*u^6 + 59504*u^7 - 498278*u^8 + 337206*u^9 + 1738254*u^10 - 2599698*u^11 - 803112*u^12 + 2379022*u^13 - 1098742*u^14 + 4545416*u^15 - 204455*u^16 - 7092604*u^17 - 1337188*u^18 + 1508320*u^19 + 4814611*u^20 + 1361896*u^21 - 2925566*u^22 - 1839532*u^23 - 800287*u^24 + 762326*u^25 + 300522*u^26 - 5154*u^27 + 150914*u^28 - 15184*u^29 + 21983*u^30 - 1735*u^31 + 1597*u^32 - 55*u^33 + 64*u^34 + u^36",
						"205892282572715305888187372081388699574863155332215892991258706313880684076894990628361123337374064457535828395456152874263005579475769897182812381 + 75548358896416081536213738899734922501316286735361622098660038263478617559964949875211680915348712032099338692095015890165391399919111393253613392*a + 298074727921439377759670787816777704787480826952413532435051685487824745818689193891194269599011097348034936943451025215067390019615090499173961431*u - 8359307338194213099775930737994582830414456355371542105506128234430807929856538257079810747479883704946152940254735886865753763763659381227014905685*u^2 + 8732138468792279427449143446807232692851513125410312873663728097960953301727798002921063445563506099862245054820009717619724920590288046856786681355*u^3 + 11719443688538040392525556783015507766440478713055403912678501155897331321385255429170760094008770685312291513638202273685537146111876809445190078496*u^4 + 85935771141810503130433459922334796292038877966223544980664359627529394949921964138190335369394460177574903333194180189238956165869214097883809083146*u^5 - 19218717152392595969201650769614932755562560321999914234575783143656083065092462521214982574018875644088788347564046060897237580839764824643143672822*u^6 - 1702912635424739602265927913242503679609508074463787246014874739839323733921618141935292966041343935947617528646130346035754052047967408539443095873526*u^7 + 2594657473337741366076994853353036481281401610890724535820637022788014175800134960368953662083717683482496579324835484085519898696979284209155455233548*u^8 + 5803549130689751410013279468144019372736714398072546666564772998402040213546983576260925308134181868163042938197890763921001096569465334681630622317738*u^9 - 13083363190012133302112240550314534302250964863254640031278803622454564947427800619538190267393339644950629691507084757863867302266273924427726888278704*u^10 - 1638332862200774753149441234159611774275934752565053542287301017759307637537747528780903936425952401993576121531380925966426265078089346357075082856762*u^11 + 12217251353626194303434753169358449972849085943912204435788664100067248271675156076183629536123937634457958556433974301363567854655425441968536469969838*u^12 - 1141245312891004286287879226385997705451783976334788462665674961602312390352589706571268737721759889774210811564769568756151335377973105934057858257708*u^13 + 20067729941503482098513798809162413059499880019363029623781743988281390765804367884731822061362681229558530518206965590449626691639013813203448156605686*u^14 - 8763047673652286353776631948241688197912902618298057533775380997121590209197533948269526532325295791041624691870807661335938837525050917715022977789874*u^15 - 36024359185256401230685887660881047909022572074740040218035995067539953784142606912933437324263304359992272754627003250239878495715117109235639184766733*u^16 - 3467238085411450918445618797823813358537383536629269454995500730112100983335314862187626916951078381248696453172714941890756889395156417102479363899377*u^17 + 12838544615778196192579709731476305497526525539504660814451575831989947278322558904928809154353716717286213838648244968970190276198437252456989903938531*u^18 + 24392791143498508730235561571751081715624994781624634216794659393656754176719009277340427186153216365692246413991777901163736995283703029892742270025947*u^19 + 3131952302140021121982403872679306288714174277139799727306472563171734497687495562404751914989385403540600630257629260224602016357327626639914504245338*u^20 - 16709335829807871659249682322254369321267509529658594571975494564406131255103779009296182487275351175287371127856833031992203752966705446783548647967086*u^21 - 9741254762795906721021740084555450802981792913149499389193098918198913176966070460428991103716375611145438260036932590675838135831910225417878087608292*u^22 - 3105181427970690535051052613179114829271795805859455926734628188680016544645641578581809098316679910433304373540358639873965789949968616559315337812704*u^23 + 4113373382269511289756248734559652723411494472818138934190328614914965539087946349027841314849592147393706615162401394881248496302847986850031002955293*u^24 + 1539534758851013241238265565799397429978450173561425109601432902433297484585223912988759180572104814831322604038528593626983526668067948618567324892659*u^25 + 126354937622231869412384933444708515944088206438404311286495964825513287999533468107063533273150367240113686359222698859513651859592131887751633523485*u^26 + 743232995554406057845499077035311815450495657294324685204315367570382216933809743923386721195854307694441027158001530710116810553019212191568751044043*u^27 - 53423939822804644890901805690536404138733221752205258024307421851810108777147171116032648434492529037516025376777017306933455645813536777044075509603*u^28 + 108253672251326547840765832218138418525893690789429109844442894240115502671253581219809684452571638312315166212829426971038545488566183665201466290341*u^29 - 7009295577423973033629008162359721334680596581363762671807953677090628635851059123397046971412152198225302991769985734795687200567249597844220914816*u^30 + 7921363792943438034005282538194505373892134157881666247563260768722163669367975122428150818665727122578573837475725578272421985771837147502802283061*u^31 - 207850147840820893586368992935530743457427686816083197412661541701599233802996115239487970235708408133115481158020037579752276631098084497344028778*u^32 + 319230137162403162528328372021620047073744009815649868599498249087603745961472805313328538778222538903564080977282479659676828537478586660312093035*u^33 + 1033999388376069941658694458723799100628087116947585829943849193723218452235483319914539000575021519323870102122751356005306299203964144824576819*u^34 + 4982987518244305821789908526443474718881558737989471473004193485230284623855924866218418721546170818948834616921794051904390731251890096380053419*u^35",
						"12151671300578081636745144335266184637489162455464395915604073442991971132721909629958176677474551517900741691831457785621628245656699885253287637 + 2437043835368260694716572222572094274236009249527794261247098008499310243869837092748763900495119742970946409422419867424690045158681012685600432*b - 15921344128582456596465634216493064103300096347421785111160002690576444406955814537357851565912817316568888760313163021897807289919696348834293005*u - 209813699886970539792225711065120580848828067079827151778814814047719763879067966705127307305384317826768212862393822995420348619273085483951296077*u^2 + 275074732480794664297974123577150211900749992416650455727711451640285659665809191753181462329523040694012064709711543733286130113323659399456669151*u^3 + 588776358608886087274379247245737243615529913197384955510695001178247489255357432118552826973384661250427227443516399418342424650129381527220071688*u^4 + 2721022335989718167619000301499435614213474448699789482530814168325482374910039911403762403190372951776862472321376149973128240620041503092503038530*u^5 - 6493731583509824066269784768290192676213695215924106506858772412232649639553373422641513979925904887243752093779496441528213839113341884563053047830*u^6 - 39324411347831706123158273689741875031536107583211094139454954361784193283189086863208736737765163128355847950774265194047647344113740119233441562670*u^7 + 98514170244561902664688624895066860847018135672982952938714112631559159748221263488447264058006994765650834952095076465993002713790103456786436717548*u^8 + 117300786819829501575077369861048445519752939018388942116242644358048164508657563663448216248230697031367038514360151955445071648916434039472277628522*u^9 - 399054353532385247813272654440975708316050067728646310101837116773412399863668855681926251809479396420110644123319609087135502665199358859376700280568*u^10 + 14241499941733200187937738914599047426512105772802149956561896606106098177738047534535983995730096740508095367348461667143249135402130603733228421038*u^11 + 380993816800931994745503575053341756004980768406922426627818743691796684466572851570789284893849692382484667194565652976738029678271510634316963309838*u^12 + 42983687869185492561226240845489173962099417616272703937357788148317278723921208667715043059515047728031183805178824701917074678990299985674836961436*u^13 + 544976178186738995726438558820177288217915128047077164103142275126673819168740521587963876187863016244922487951360149306381257910838223986431587798238*u^14 - 444409632263140025389592991095872934215285694168371869721191794322738703893829542834773998298304779738648318932555203628083074391566777295410253738738*u^15 - 1109392085308409175374742812441760194962429855814611116475352662906737925584354078815751600342510262435175480732688169524800912068035648703969397824477*u^16 - 22964809031546751046112209782112862719936096013522743016238407888166289002696881513278494410070688926496226405875149702108796530393993489224174820725*u^17 + 512716013215731070771268142471719687125997743666232546100773402531841072479522423621369560895474864547868908314260708589012070989975069276241409623883*u^18 + 749842257485160991066254896479141358904226896710378948823132117947912872334706278881596940333157186793338467768988572827492216792609439261237492484911*u^19 + 4316038566127516073167633617206843634212724217649301004274751702713435422726027790243434208549391902402809330387858274484924624308054834825154863794*u^20 - 565600098947371297600291578555327056096116478843897936413521472873721060397765114448800125076540086741982422163875769742094216948687908547838486920622*u^21 - 311974816352299889328224554254659685526368277563305662858830143518746836238466623943909273493039952732560298613791839978151229593154628693240833562220*u^22 - 73885109657186704200636113110157039180285261063107037459083719848312769150716637259399507816852255177175303924289960249608997074871568607529721335672*u^23 + 135126225631577186895198445070985245837185279663099295403849324393412899858622769891022238022202517453390393765478597979576265130741372485490645245469*u^24 + 48858408164346611006069801739698584909060860463233537152978801340483222805724983806327203243870912067917874269774351361480863631863889080579723908919*u^25 + 7594305239308334815271635015881811227619095627068844422641966589254397291817609256980684451858044503656868875798913224624982444613778401171649307885*u^26 + 22790211666219668819841676275914391410611626254815927904519313588112114998453913593799270966296315480690561152556542533460719364824503607104853101279*u^27 - 1114945605905132966900494292446114266497910332010876797171633168225792629614660115836933089364620545483513910335091197231376958936245520901560500259*u^28 + 3316341547914348528967753184726695300536263215681187088368443784220537666790388679080060275764144612773211705511178395583699519580239672058489656505*u^29 - 177170387319664803916351385777745424088538697891686950509132620334798403637352461003787270030601178718107369594833310858677391263618019730059239296*u^30 + 243954898016068867216609527731370859687847021991918400280500509332491554402446045090553231132521386685136160282536687437081863396075171574491728765*u^31 - 4829278686216928452132351649422801553504916544056004932083386719635968126786801577091798246494845862641201452199677184148176920548348292907748310*u^32 + 9870973108383827062975573778164590303103881854558659954029094699764446826642286253635871070413364907225699302723940857651849956154723062204003855*u^33 + 56737024445525239198106475019205906308066112186224292196006998032326962982801919517149209022621984074336325936795301476492808955499412733682083*u^34 + 153928873975580121893278258687817270399162377022861677109333238528301148276632376382525778881241619592629757269731678235890238854154313798409591*u^35"
					],
					"VariableOrder":[
						"u",
						"a",
						"b"
					],
					"Characteristic":0,
					"KnownGroebner":[],
					"Status":[
						"vCompNormalize"
					],
					"MonomialOrder":"lex",
					"IsHomogeneous":false,
					"IsZeroDim":true,
					"IdealDimension":0,
					"ZeroDimensionalVars":[
						"u",
						"a",
						"b"
					],
					"Timings":{
						"TimingmagmaVCompNormalize":4.95e-4,
						"TimingComplexVolumeN":5.506881,
						"TimingObstruction":3.1526e-2,
						"TiminguValues_ij":3.644e-3,
						"TiminguPolys_ij_N":0.238609
					},
					"ComplexVolumeN":[
						-18.993882150691953587118650966094319269013752262242021011046116954129055450165867405676093311756163988702089955597129225083,
						"-9.5739584330864833257964918868378088799888794175297482549430366953452502884415036962648206120119916578465134494032019`106.79326976850604 + 12.5540725870738582548664612613457594814176780867893350564137811107092616107783751805084442577689442768870860366288601`106.91096286630967*I",
						"-9.57395843308648332579649188683780887998887941752974825494303669534525028844150369626482061201199165784651344933748670819583728202763516`110.56463669666222 - 12.554072587073858254866461261345759481417678086789335056413781110709261610778375180508444257768944276887086037089156032034931644980739872`110.68232979446596*I",
						"3.936126228321494870035769237124643637049820631578696917820988933750018138309585902690246810754414327052027848026605547266293688052062166`119.77540737118254 + 0.488131680282206541968886662488450064541723187732484421288808113238181238409007236319078228920484990166643523534365574872815544561286349`118.86888950497878*I",
						"3.936126228321494870035769237124643637049820631578696917820988933750018138309585902690246810754414327052027848026605547291746025368999975`116.367862070472 - 0.488131680282206541968886662488450064541723187732484421288808113238181238409007236319078228920484990166643523534365574877747437521373469`115.46133005592613*I",
						-14.0796893414583883194369923350010816229636569540992671248428339886123138310907645256999829979102692908316214570866737126439,
						"-7.1750228050015746934888968146222116374252587463902490884368664877287250420332463675238630915917143963698871181987097`100.03352898026108 + 0.3994533403189902172765772200417866696288687896623392619281897692558443784160726364997663647843050822966057166324653`98.77917175167507*I",
						"-7.175022805001574693488896814622211637425258746390249088436866487728725042033246367523863091591714396414337779062419922574823595498709849`121.7344240478658 - 0.399453340318990217276577220041786669628868789662339261928189769255844378416072636499766364784305082306379733990808937749247254447747869`120.51778638701826*I",
						"-12.288063926749735536270213056279625974842859221972004247725324832139522189788729841575320888363712766747900424159570128755432348168164985`114.7960245849309 - 3.879871505549945297397836141896780589352819312032986890038051956113637161378357040240485566476638536114441165269242189000649305307246296`114.29535846637557*I",
						"-12.288063926749735536270213056279625974842859221972004247725324832139522189788729841575320888363712766747900424159570127625548746605628331`115.95825272392102 + 3.8798715055499452973978361418967805893528193120329868900380519561136371613783570402404855664766385361144411652692421871418759466580002`115.45764991468276*I",
						"-10.671261119131386052898291929598852114424614987510394744258683487651173870794804409585223830921741068960872235724031016468109882081140862`107.20731674649305 + 0.809202332849391046133631742786876246154266000349370912952985775875863283053245335653867516293004994739997942409878876204117199890119057`106.08715812566946*I",
						"-10.671261119131386052898291929598852114424614987510394744258683487651173870794804409585223830921741068960872235888128860671742434861031897`121.11770524827922 - 0.80920233284939104613363174278687624615426600034937091295298577587586328305324533565386751629300499473999794222012515593046882988502842`119.99825716942337*I",
						"1.8660418106200028719549990133738255954390422195794471808190679269568546322897867776591138504114651866240290286616645`99.1529896982226 + 3.9783707973332338752659010705095013961836045749854475723468111581974216976970694044742778606326643809632789202264215`99.48177358623947*I",
						"1.866041810620002871954999013373825595439042219579447180819067926956854632289786777659113850411465186734700180461934151615235506791343199`107.20065120430104 - 3.978370797333233875265901070509501396183604574985447572346811158197421697697069404474277860632664381083953761535431160924909835296688526`107.5294350923179*I",
						"-2.478157804121927803350403346819800980789345822418932571953593991112308534786849208882884788313322608263688272789743815062009263726288633`123.09378432396485 + 0.363221289801177274677744734292491188497307950369870674131481954342013133808289428563214091789478060702306020581054245187699692385835069`122.28356313725205*I",
						"-2.478157804121927803350403346819800980789345822418932571953593991112308534786849208882884788313322608263688272789743849730231161934805`114.77609218802377 - 0.363221289801177274677744734292491188497307950369870674131481954342013133808289428563214091789478060702306020581054286246204688599930154`113.9421345286955*I",
						-7.22329391712023377524046582728640180065457911723223293659979034208858669121382984912709784360943823064958579957994409,
						"-0.471691924109020182548174302040316632802288287975407032284757799065968432136910341572857125028360944475598158790467556826636558980936958`110.94791098440922 + 10.133635035480126726976677295746572854264583976523983436745990316339935341039887571782561678959954789399577468417571411430475861905546467`112.28001780277663*I",
						"-0.471691924109020182548174302040316632802288287975407032284757799065968432136910341572857125028360944475598158790467728733328315677693045`113.37760194503439 - 10.133635035480126726976677295746572854264583976523983436745990316339935341039887571782561678959954789399577468417571242480143142148706391`114.70970876875835*I",
						"-0.98172482479704378287565117261210603998808383779083830859456529978387646434601196474322989428836318829508245125870513054444552149114783`113.9355856598051 + 1.294469791604320148851873823872411449718173281653379223842330965448329680589090189265548828883209089460841817984361667994979744751468697`114.05594487622605*I",
						"-0.981724824797043782875651172612106039988083837790838308594565299783876464346011964743229894288363188295082451258705133190966846597062172`114.21502760101883 - 1.294469791604320148851873823872411449718173281653379223842330965448329680589090189265548828883209089460841817984361667831502354617384434`114.33512974801356*I",
						"0.806423420675708733923515220227847252268823514072759379148654801084604554447345404026048901847507741230640819972639338627306559833842233`110.3556810762866 - 2.954343338484031887694037159931347926560628710941938939347072613353059944265416698363688957780452823337557886363049266656511007822759284`110.91957890930333*I",
						"0.806423420675708733923515220227847252268823514072759379148654801084604554447345404026048901847507741230640819972624860282659247142738222`113.22048787289287 + 2.95434333848403188769403715993134792656062871094193893934707261335305994426541669836368895778045282333755788636307716951565917369350942`113.78438570641369*I",
						-0.73803523118798276364339397232686896448025706306512705576321337731158642321957680650372107942686354707850066043046713992,
						"0.624832211820127122046040002342169259297533065319691944843531254158430410232708373311213242779955329600041181091349598373271590796842402`113.57332927334976 - 2.041695032263689798762889667450179679119929966983391372928423123470929800582769088820684921315155776038187208795974399252516520255587136`114.08755673580013*I",
						"0.624832211820127122046040002342169259297533065319691944843531254158430410232708373311213242779955329600041181091382440597981540249149154`108.82031146340996 + 2.041695032263689798762889667450179679119929966983391372928423123470929800582769088820684921315155776038187208795987721944227677891653647`109.33453892496965*I",
						"-3.577090691170415447801988447373032520225096608598898022187452599387240092480485376488548111612985607634008149681303546484856472130547528`120.25101193432666 + 3.066277139402127994001049146967947627591849710419101568193294457795680600215731276091813768564549888433655916898582222627520085513554334`120.18448952159216*I",
						"-3.577090691170415447801988447373032520225096608598898022187452599387240092480485376488548111612985607634008149681303546484855606733907866`122.14995293962154 - 3.066277139402127994001049146967947627591849710419101568193294457795680600215731276091813768564549888433655916898582222627520345573482991`122.09963734179523*I",
						-2.16434997041710098533329617191026909162708007947840816859603394246255841784910233998511364642718271762508298533070,
						"2.629307376227537136240278331477918421130906548754609385583746435191037762143911075738665387074829902065669323196748811855019947865508832`110.04116168486433 - 6.16336319526734388525633970530900908224979714330889607695269792863910145236784775684825532264704047966488758949956085323401260877476074`110.41113809145273*I",
						"2.629307376227537136240278331477918421130906548754609385583746435191037762143911075738665387074829902065669323196748760913423424802447032`112.20401439028367 + 6.163363195267343885256339705309009082249797143308896076952697928639101452367847756848255322647040479664887589499555058196196020341480433`112.57861364137769*I",
						-5.20603797016442402179804314516099925272248338270684617792668405405113213676649269139085392076769795257203577238571321594,
						"-6.457275931537271355967275256099933552097753785057851963150260350741943153248486625130136923226982140839483526998711633198887423535636916`109.05845312236612 - 5.838351756740017191323916966688282333117343681711118223874525482462430797571998703074679781618983021487901011675330575366895974486863629`109.01469403473297*I",
						"-6.457275931537271355967275256099933552097753785057851963150260350741943153248486625130136923226982140839483526998938635613633395775235049`111.08193874639454 + 5.838351756740017191323916966688282333117343681711118223874525482462430797571998703074679781618983021487901011673743169027537733337743856`111.0381892889363*I",
						"-8.475273405882500122885099632412917130552211240765056691997569144562668327962333525730715406378970040112337421328454623705854339065876882`110.77131068273972 - 5.021131770349948677225986678483833813947838219949631493709975959149417609317881874779453205427800214509366773848311652211317065339312328`110.54395858441082*I",
						"-8.475273405882500122885099632412917130552211240765056691997569144562668327962333525730715406378970040112337421328138269678460548041658727`109.7828747101813 + 5.021131770349948677225986678483833813947838219949631493709975959149417609317881874779453205427800214509366773848303141111350207261640214`109.55552261185237*I"
					],
					"GeometricComponent":"{2, 3}",
					"SortedReprnIndices":"{2, 3, 18, 19, 31, 30, 34, 33, 36, 35, 13, 14, 10, 9, 27, 28, 23, 22, 26, 25, 20, 21, 11, 12, 4, 5, 7, 8, 15, 16, 1, 6, 17, 32, 29, 24}",
					"Abelian":false,
					"Obstruction":-1,
					"ij_list":[
						[
							"{1, 2}"
						],
						[
							"{1, 3}"
						],
						[
							"{1, 4}"
						],
						[
							"{1, 5}"
						],
						[
							"{1, 6}"
						],
						[
							"{1, 7}"
						],
						[
							"{1, 8}"
						],
						[
							"{1, 9}"
						],
						[
							"{1, 10}"
						],
						[
							"{1, 11}"
						],
						[
							"{1, 12}"
						],
						[
							"{2, 3}"
						],
						[
							"{2, 4}"
						],
						[
							"{2, 5}"
						],
						[
							"{2, 6}"
						],
						[
							"{2, 7}"
						],
						[
							"{2, 8}"
						],
						[
							"{2, 9}"
						],
						[
							"{2, 10}"
						],
						[
							"{2, 11}"
						],
						[
							"{2, 12}"
						],
						[
							"{3, 4}"
						],
						[
							"{3, 5}"
						],
						[
							"{3, 6}"
						],
						[
							"{3, 7}"
						],
						[
							"{3, 8}"
						],
						[
							"{3, 9}"
						],
						[
							"{3, 10}"
						],
						[
							"{3, 11}"
						],
						[
							"{3, 12}"
						],
						[
							"{4, 5}"
						],
						[
							"{4, 6}",
							"{4, 7}"
						],
						[
							"{4, 8}"
						],
						[
							"{4, 9}"
						],
						[
							"{4, 10}"
						],
						[
							"{4, 11}"
						],
						[
							"{4, 12}"
						],
						[
							"{5, 6}"
						],
						[
							"{5, 7}"
						],
						[
							"{5, 8}"
						],
						[
							"{5, 9}"
						],
						[
							"{5, 10}"
						],
						[
							"{5, 11}"
						],
						[
							"{5, 12}"
						],
						[
							"{6, 7}"
						],
						[
							"{6, 8}"
						],
						[
							"{6, 9}"
						],
						[
							"{6, 10}"
						],
						[
							"{6, 11}"
						],
						[
							"{6, 12}"
						],
						[
							"{7, 8}",
							"{8, 9}"
						],
						[
							"{7, 9}"
						],
						[
							"{7, 10}"
						],
						[
							"{7, 11}"
						],
						[
							"{7, 12}"
						],
						[
							"{8, 10}"
						],
						[
							"{8, 11}",
							"{8, 12}"
						],
						[
							"{9, 10}"
						],
						[
							"{9, 11}"
						],
						[
							"{9, 12}"
						],
						[
							"{10, 11}"
						],
						[
							"{10, 12}"
						],
						[
							"{11, 12}"
						]
					],
					"uPolys_ij_N":[
						"1 + 1288*u + 16358*u^2 + 102720*u^3 + 433229*u^4 + 1385504*u^5 + 3573036*u^6 + 7701924*u^7 + 14207226*u^8 + 22824212*u^9 + 32403720*u^10 + 41180276*u^11 + 47401908*u^12 + 49968688*u^13 + 48735662*u^14 + 44384994*u^15 + 38025867*u^16 + 30785546*u^17 + 23573990*u^18 + 17035524*u^19 + 11582905*u^20 + 7416896*u^21 + 4520202*u^22 + 2684750*u^23 + 1600691*u^24 + 971050*u^25 + 587692*u^26 + 339942*u^27 + 180040*u^28 + 84500*u^29 + 34323*u^30 + 11819*u^31 + 3371*u^32 + 771*u^33 + 134*u^34 + 16*u^35 + u^36",
						"1 + 1288*u + 16358*u^2 + 102720*u^3 + 433229*u^4 + 1385504*u^5 + 3573036*u^6 + 7701924*u^7 + 14207226*u^8 + 22824212*u^9 + 32403720*u^10 + 41180276*u^11 + 47401908*u^12 + 49968688*u^13 + 48735662*u^14 + 44384994*u^15 + 38025867*u^16 + 30785546*u^17 + 23573990*u^18 + 17035524*u^19 + 11582905*u^20 + 7416896*u^21 + 4520202*u^22 + 2684750*u^23 + 1600691*u^24 + 971050*u^25 + 587692*u^26 + 339942*u^27 + 180040*u^28 + 84500*u^29 + 34323*u^30 + 11819*u^31 + 3371*u^32 + 771*u^33 + 134*u^34 + 16*u^35 + u^36",
						"-1 + 40*u - 156*u^2 + 84*u^3 + 629*u^4 - 1248*u^5 - 372*u^6 + 3676*u^7 - 2970*u^8 - 4364*u^9 + 9108*u^10 - 1004*u^11 - 11920*u^12 + 10496*u^13 + 5990*u^14 - 15262*u^15 + 4429*u^16 + 10802*u^17 - 10236*u^18 - 2376*u^19 + 8693*u^20 - 3040*u^21 - 3934*u^22 + 3766*u^23 + 365*u^24 - 2110*u^25 + 758*u^26 + 618*u^27 - 550*u^28 - 36*u^29 + 207*u^30 - 57*u^31 - 41*u^32 + 27*u^33 - 4*u^35 + u^36",
						"64 - 2896*u + 21816*u^2 + 9375*u^3 - 419399*u^4 + 90320*u^5 + 6075840*u^6 - 17601924*u^7 + 23487752*u^8 - 38317776*u^9 + 89612120*u^10 - 90317774*u^11 - 120533230*u^12 + 423965504*u^13 - 334553592*u^14 - 421624070*u^15 + 1415696546*u^16 - 1912395458*u^17 + 1648242588*u^18 - 987349683*u^19 + 420806267*u^20 - 140983764*u^21 + 62853048*u^22 - 49590926*u^23 + 36972062*u^24 - 20330974*u^25 + 8137700*u^26 - 2402807*u^27 + 552695*u^28 - 128834*u^29 + 44720*u^30 - 17971*u^31 + 5789*u^32 - 1339*u^33 + 212*u^34 - 21*u^35 + u^36",
						"-35902921 - 266213979*u - 1389774699*u^2 - 7361962558*u^3 - 2495502249*u^4 + 77657115986*u^5 + 392029108406*u^6 + 1239282945576*u^7 + 2888863158736*u^8 + 4054347629922*u^9 + 3541011402020*u^10 + 1745732900104*u^11 + 119684052962*u^12 - 595531707990*u^13 - 612985399666*u^14 - 397521979412*u^15 - 205464893625*u^16 - 90466435801*u^17 - 34162488993*u^18 - 10585600016*u^19 - 2333269389*u^20 - 48579868*u^21 + 319741056*u^22 + 237434128*u^23 + 122377265*u^24 + 52854563*u^25 + 20169283*u^26 + 6957052*u^27 + 2192256*u^28 + 636513*u^29 + 169990*u^30 + 41092*u^31 + 8697*u^32 + 1536*u^33 + 211*u^34 + 20*u^35 + u^36",
						"1 + 15*u + 103*u^2 + 562*u^3 + 2749*u^4 + 10884*u^5 + 37248*u^6 + 114320*u^7 + 325006*u^8 + 852306*u^9 + 1996286*u^10 + 4093736*u^11 + 7300912*u^12 + 11408466*u^13 + 15782560*u^14 + 19527536*u^15 + 21809731*u^16 + 22131115*u^17 + 20556345*u^18 + 17524202*u^19 + 13793905*u^20 + 10025362*u^21 + 6757844*u^22 + 4218456*u^23 + 2443643*u^24 + 1311487*u^25 + 650687*u^26 + 298466*u^27 + 125348*u^28 + 48389*u^29 + 16792*u^30 + 5286*u^31 + 1445*u^32 + 346*u^33 + 67*u^34 + 10*u^35 + u^36",
						"-119 - 565*u + 1893*u^2 + 12244*u^3 + 9165*u^4 - 48108*u^5 - 174282*u^6 - 5150*u^7 + 1315022*u^8 + 1675316*u^9 - 1703448*u^10 - 2607674*u^11 + 310392*u^12 + 1150918*u^13 + 1075374*u^14 + 4811862*u^15 + 4230519*u^16 - 3751559*u^17 - 1999931*u^18 + 4620578*u^19 + 4856473*u^20 + 3724442*u^21 - 2425188*u^22 - 5022472*u^23 + 684463*u^24 + 2154951*u^25 - 176563*u^26 - 498078*u^27 + 42074*u^28 + 69371*u^29 - 7090*u^30 - 5874*u^31 + 727*u^32 + 282*u^33 - 41*u^34 - 6*u^35 + u^36",
						"1 + 7*u + 17*u^2 + 20*u^3 - 51*u^4 - 238*u^5 - 78*u^6 + 464*u^7 + 416*u^8 + 556*u^9 - 18*u^10 - 3674*u^11 - 2562*u^12 + 5478*u^13 + 6374*u^14 + 1134*u^15 - 6461*u^16 - 18355*u^17 - 1011*u^18 + 36852*u^19 + 12199*u^20 - 43442*u^21 - 18546*u^22 + 34866*u^23 + 16363*u^24 - 19755*u^25 - 9649*u^26 + 7900*u^27 + 3922*u^28 - 2179*u^29 - 1088*u^30 + 394*u^31 + 197*u^32 - 42*u^33 - 21*u^34 + 2*u^35 + u^36",
						"419713 + 2630613*u - 4928109*u^2 - 31299360*u^3 + 49596313*u^4 + 206136098*u^5 - 213233174*u^6 - 665208258*u^7 + 608102292*u^8 + 1204242258*u^9 - 1225817666*u^10 - 1256400750*u^11 + 1665542346*u^12 + 638239380*u^13 - 1441223700*u^14 + 30673452*u^15 + 752593925*u^16 - 213027363*u^17 - 242386523*u^18 + 127477546*u^19 + 48147949*u^20 - 44764050*u^21 - 3803972*u^22 + 11009400*u^23 - 1207019*u^24 - 1856103*u^25 + 528695*u^26 + 190146*u^27 - 101802*u^28 - 6897*u^29 + 11846*u^30 - 1110*u^31 - 793*u^32 + 192*u^33 + 15*u^34 - 10*u^35 + u^36",
						"1359 + 12267*u - 31679*u^2 - 297418*u^3 + 635013*u^4 + 4109372*u^5 - 1341552*u^6 - 18128988*u^7 + 327286*u^8 + 43889870*u^9 + 1202802*u^10 - 68753616*u^11 + 1471504*u^12 + 75638450*u^13 - 8073796*u^14 - 61277134*u^15 + 12633901*u^16 + 37620957*u^17 - 11855371*u^18 - 17651922*u^19 + 7779429*u^20 + 6214090*u^21 - 3761376*u^22 - 1554822*u^23 + 1382221*u^24 + 213437*u^25 - 382529*u^26 + 20164*u^27 + 73926*u^28 - 19151*u^29 - 7364*u^30 + 4348*u^31 - 225*u^32 - 370*u^33 + 127*u^34 - 18*u^35 + u^36",
						"1 + 15*u - 93*u^2 - 1042*u^3 + 3805*u^4 + 60924*u^5 + 207976*u^6 + 17792*u^7 - 1858806*u^8 - 5432326*u^9 - 2716598*u^10 + 23360924*u^11 + 74090292*u^12 + 90003450*u^13 - 45862144*u^14 - 382371744*u^15 - 716230605*u^16 - 579739005*u^17 + 444515861*u^18 + 2283432418*u^19 + 4255599869*u^20 + 5478620262*u^21 + 5472774652*u^22 + 4428307732*u^23 + 2959796263*u^24 + 1648956039*u^25 + 768122927*u^26 + 298887382*u^27 + 96726312*u^28 + 25832441*u^29 + 5626668*u^30 + 982566*u^31 + 134161*u^32 + 13790*u^33 + 1003*u^34 + 46*u^35 + u^36",
						"1 + 1626228*u + 3843902*u^2 - 60209332*u^3 + 133128685*u^4 - 54269056*u^5 - 413733508*u^6 + 1281955716*u^7 - 608438742*u^8 - 2143250412*u^9 + 3531993752*u^10 - 1280949148*u^11 - 1876951260*u^12 + 3958683888*u^13 - 6052201762*u^14 + 8425077138*u^15 - 9190505449*u^16 + 7254939942*u^17 - 3564250118*u^18 + 83572392*u^19 + 1810313153*u^20 - 2035145464*u^21 + 1410493450*u^22 - 729135738*u^23 + 308845359*u^24 - 115823842*u^25 + 39703872*u^26 - 11613886*u^27 + 2442228*u^28 - 200800*u^29 - 74317*u^30 + 34135*u^31 - 6613*u^32 + 575*u^33 + 26*u^34 - 12*u^35 + u^36",
						"-1 + 40*u - 156*u^2 + 84*u^3 + 629*u^4 - 1248*u^5 - 372*u^6 + 3676*u^7 - 2970*u^8 - 4364*u^9 + 9108*u^10 - 1004*u^11 - 11920*u^12 + 10496*u^13 + 5990*u^14 - 15262*u^15 + 4429*u^16 + 10802*u^17 - 10236*u^18 - 2376*u^19 + 8693*u^20 - 3040*u^21 - 3934*u^22 + 3766*u^23 + 365*u^24 - 2110*u^25 + 758*u^26 + 618*u^27 - 550*u^28 - 36*u^29 + 207*u^30 - 57*u^31 - 41*u^32 + 27*u^33 - 4*u^35 + u^36",
						"-1 + 40*u - 156*u^2 + 84*u^3 + 629*u^4 - 1248*u^5 - 372*u^6 + 3676*u^7 - 2970*u^8 - 4364*u^9 + 9108*u^10 - 1004*u^11 - 11920*u^12 + 10496*u^13 + 5990*u^14 - 15262*u^15 + 4429*u^16 + 10802*u^17 - 10236*u^18 - 2376*u^19 + 8693*u^20 - 3040*u^21 - 3934*u^22 + 3766*u^23 + 365*u^24 - 2110*u^25 + 758*u^26 + 618*u^27 - 550*u^28 - 36*u^29 + 207*u^30 - 57*u^31 - 41*u^32 + 27*u^33 - 4*u^35 + u^36",
						"1 + 15*u + 103*u^2 + 562*u^3 + 2749*u^4 + 10884*u^5 + 37248*u^6 + 114320*u^7 + 325006*u^8 + 852306*u^9 + 1996286*u^10 + 4093736*u^11 + 7300912*u^12 + 11408466*u^13 + 15782560*u^14 + 19527536*u^15 + 21809731*u^16 + 22131115*u^17 + 20556345*u^18 + 17524202*u^19 + 13793905*u^20 + 10025362*u^21 + 6757844*u^22 + 4218456*u^23 + 2443643*u^24 + 1311487*u^25 + 650687*u^26 + 298466*u^27 + 125348*u^28 + 48389*u^29 + 16792*u^30 + 5286*u^31 + 1445*u^32 + 346*u^33 + 67*u^34 + 10*u^35 + u^36",
						"769 + 7993*u + 33127*u^2 + 110762*u^3 + 328149*u^4 + 943674*u^5 + 1763930*u^6 + 4021880*u^7 + 5744638*u^8 + 10002078*u^9 + 12763020*u^10 + 15102424*u^11 + 21300790*u^12 + 15267554*u^13 + 24969598*u^14 + 12798538*u^15 + 19084891*u^16 + 10980717*u^17 + 8480185*u^18 + 8675056*u^19 + 1659763*u^20 + 4677200*u^21 + 164796*u^22 + 1393290*u^23 + 202109*u^24 + 196705*u^25 + 115093*u^26 + 6414*u^27 + 25068*u^28 + 1537*u^29 + 1626*u^30 + 880*u^31 - 31*u^32 + 76*u^33 + 9*u^34 + u^36",
						"119011 + 808384*u + 1690477*u^2 + 1347341*u^3 + 2575177*u^4 + 6107708*u^5 + 11801514*u^6 + 30883682*u^7 + 25824936*u^8 + 7725490*u^9 + 54961792*u^10 + 65935718*u^11 + 200526524*u^12 + 509135662*u^13 + 621178292*u^14 + 816139836*u^15 + 882117459*u^16 + 657669260*u^17 + 567686161*u^18 + 405562511*u^19 + 237216279*u^20 + 193775748*u^21 + 123245800*u^22 + 60204782*u^23 + 26806621*u^24 + 5778722*u^25 - 40991*u^26 - 539241*u^27 - 467966*u^28 - 125398*u^29 - 20094*u^30 - 3782*u^31 + 1110*u^32 + 79*u^33 + 73*u^34 + 3*u^35 + u^36",
						"-19 + 168*u + 173*u^2 - 2607*u^3 - 2857*u^4 + 10684*u^5 + 13780*u^6 - 18156*u^7 - 26750*u^8 + 12046*u^9 + 17294*u^10 - 2498*u^11 + 7340*u^12 + 5016*u^13 - 10054*u^14 - 12982*u^15 - 9811*u^16 + 10362*u^17 + 14555*u^18 - 3929*u^19 - 1175*u^20 + 5958*u^21 - 5024*u^22 - 4980*u^23 + 3061*u^24 + 1996*u^25 - 951*u^26 - 531*u^27 + 50*u^28 + 68*u^29 + 60*u^30 + 4*u^31 - 18*u^32 - u^33 + 5*u^34 + u^35 + u^36",
						"41 - 99*u - 983*u^2 + 4144*u^3 + 8375*u^4 - 54136*u^5 - 13798*u^6 + 328008*u^7 - 156092*u^8 - 1072994*u^9 + 1004534*u^10 + 2037852*u^11 - 2868302*u^12 - 2092648*u^13 + 4700986*u^14 + 599960*u^15 - 4516215*u^16 + 934001*u^17 + 2406939*u^18 - 934172*u^19 - 673263*u^20 + 279726*u^21 + 101110*u^22 + 9358*u^23 - 16421*u^24 - 25173*u^25 + 5699*u^26 + 5158*u^27 - 844*u^28 + 185*u^29 - 236*u^30 - 228*u^31 + 111*u^32 + 36*u^33 - 17*u^34 - 2*u^35 + u^36",
						"-124837 + 1172540*u - 2107424*u^2 + 736468*u^3 + 11225607*u^4 - 18382882*u^5 + 27786082*u^6 - 16574500*u^7 + 254609550*u^8 - 608079004*u^9 + 579179718*u^10 + 356211206*u^11 - 1455167732*u^12 + 669993480*u^13 - 113381894*u^14 + 459909240*u^15 + 366265775*u^16 - 215367410*u^17 - 88367508*u^18 - 176303732*u^19 - 62803813*u^20 + 16543494*u^21 + 14926788*u^22 + 27211092*u^23 + 9958803*u^24 + 4447696*u^25 + 1343754*u^26 - 178504*u^27 + 72554*u^28 - 91436*u^29 + 7875*u^30 - 7419*u^31 + 967*u^32 - 223*u^33 + 54*u^34 - 2*u^35 + u^36",
						"2709064 + 17405392*u + 58695894*u^2 + 230526983*u^3 + 563850531*u^4 + 1432510238*u^5 + 3014020008*u^6 + 5659879008*u^7 + 9935052530*u^8 + 15468709022*u^9 + 22053618914*u^10 + 28801198464*u^11 + 34037127830*u^12 + 36849914680*u^13 + 36600362140*u^14 + 33258275278*u^15 + 27699248394*u^16 + 21118058672*u^17 + 14740757986*u^18 + 9436990391*u^19 + 5540557871*u^20 + 2985448950*u^21 + 1477144554*u^22 + 670461098*u^23 + 279084628*u^24 + 106293906*u^25 + 36901450*u^26 + 11652309*u^27 + 3325529*u^28 + 852140*u^29 + 195996*u^30 + 39881*u^31 + 7055*u^32 + 1087*u^33 + 136*u^34 + 13*u^35 + u^36",
						"64 - 2896*u + 21816*u^2 + 9375*u^3 - 419399*u^4 + 90320*u^5 + 6075840*u^6 - 17601924*u^7 + 23487752*u^8 - 38317776*u^9 + 89612120*u^10 - 90317774*u^11 - 120533230*u^12 + 423965504*u^13 - 334553592*u^14 - 421624070*u^15 + 1415696546*u^16 - 1912395458*u^17 + 1648242588*u^18 - 987349683*u^19 + 420806267*u^20 - 140983764*u^21 + 62853048*u^22 - 49590926*u^23 + 36972062*u^24 - 20330974*u^25 + 8137700*u^26 - 2402807*u^27 + 552695*u^28 - 128834*u^29 + 44720*u^30 - 17971*u^31 + 5789*u^32 - 1339*u^33 + 212*u^34 - 21*u^35 + u^36",
						"-103041 + 2960262*u + 24446834*u^2 + 51088638*u^3 - 67534557*u^4 - 477363412*u^5 - 764668480*u^6 + 192734806*u^7 + 2690757054*u^8 + 4197409048*u^9 + 1586876526*u^10 - 4621593606*u^11 - 11145810264*u^12 - 11847916828*u^13 + 1057609196*u^14 + 19230658628*u^15 + 16681536303*u^16 - 5147115228*u^17 - 11163891580*u^18 + 2161947798*u^19 + 6115094685*u^20 - 491130482*u^21 - 2061705740*u^22 + 174281690*u^23 + 531411975*u^24 + 3777480*u^25 - 67965608*u^26 - 1922800*u^27 + 4865752*u^28 + 86638*u^29 - 189385*u^30 + 10157*u^31 + 6283*u^32 - 287*u^33 - 74*u^34 + 10*u^35 + u^36",
						"52112032136 + 387699154644*u + 1119468564988*u^2 + 5779024810213*u^3 + 15992721303559*u^4 + 32117829012232*u^5 + 81079935596840*u^6 + 101698295028828*u^7 + 64604504173552*u^8 + 64030423799926*u^9 - 96612475657564*u^10 - 149470638573662*u^11 + 88844322230156*u^12 + 68544792881376*u^13 - 37896424128454*u^14 - 11377846566082*u^15 + 8855580626462*u^16 + 490636485620*u^17 - 1032757142070*u^18 + 4264609087*u^19 + 80883307505*u^20 - 2346234180*u^21 - 1968400164*u^22 - 839719068*u^23 + 263298250*u^24 - 14160226*u^25 + 4205508*u^26 - 1065375*u^27 - 494415*u^28 + 306064*u^29 - 73072*u^30 + 16343*u^31 - 2657*u^32 + 173*u^33 + 24*u^34 - 5*u^35 + u^36",
						"8 + 100*u + 444*u^2 + 1029*u^3 + 1905*u^4 + 3348*u^5 + 2886*u^6 - 1722*u^7 - 4088*u^8 - 2406*u^9 - 5698*u^10 - 9826*u^11 - 4082*u^12 + 12762*u^13 + 32088*u^14 + 20150*u^15 - 30706*u^16 - 51496*u^17 - 4890*u^18 + 41523*u^19 + 29459*u^20 - 9900*u^21 - 23648*u^22 - 7698*u^23 + 8010*u^24 + 7424*u^25 + 42*u^26 - 2697*u^27 - 1101*u^28 + 360*u^29 + 430*u^30 + 69*u^31 - 71*u^32 - 35*u^33 + 2*u^34 + 5*u^35 + u^36",
						"8803 + 119646*u + 536554*u^2 + 710876*u^3 - 1259507*u^4 - 4945252*u^5 - 7269210*u^6 - 6256336*u^7 + 6380948*u^8 + 30191198*u^9 + 57241820*u^10 + 80832690*u^11 + 88554128*u^12 + 84651818*u^13 + 68009008*u^14 + 46037550*u^15 + 28536697*u^16 + 14939588*u^17 + 8605550*u^18 + 4177050*u^19 + 2884457*u^20 + 2831520*u^21 + 2886088*u^22 + 2079580*u^23 + 999577*u^24 + 242420*u^25 + 44518*u^26 + 50768*u^27 + 26016*u^28 - 1288*u^29 - 3377*u^30 - 11*u^31 + 259*u^32 + 25*u^33 + 6*u^34 + 6*u^35 + u^36",
						"-6283 - 96153*u - 305947*u^2 + 975022*u^3 + 2234871*u^4 - 4707856*u^5 - 7032702*u^6 + 15454518*u^7 + 8727644*u^8 - 25393534*u^9 + 35508894*u^10 - 11345672*u^11 - 31229634*u^12 - 2328876*u^13 - 14233692*u^14 - 7538984*u^15 - 11776339*u^16 - 3036779*u^17 + 2120965*u^18 - 3398918*u^19 - 5384657*u^20 - 1964128*u^21 - 657238*u^22 - 674282*u^23 - 322485*u^24 - 205691*u^25 - 134801*u^26 - 65690*u^27 - 12582*u^28 - 2665*u^29 - 950*u^30 - 26*u^31 + 101*u^32 - 20*u^33 - 21*u^34 + u^36",
						"26557503677 + 68568349628*u + 38738706517*u^2 + 80476451641*u^3 + 119446632389*u^4 + 29017343398*u^5 + 45578812408*u^6 - 73340034380*u^7 - 98909071646*u^8 - 78032801092*u^9 - 41738826784*u^10 - 8401307564*u^11 + 1855223520*u^12 + 3240735212*u^13 + 1254905830*u^14 + 297411506*u^15 + 32021519*u^16 - 17488522*u^17 - 47551481*u^18 - 47882137*u^19 - 26327231*u^20 - 5037970*u^21 + 3013932*u^22 + 3248840*u^23 + 1280105*u^24 + 85880*u^25 - 173923*u^26 - 78945*u^27 - 3644*u^28 + 11840*u^29 + 4690*u^30 + 148*u^31 - 406*u^32 - 145*u^33 - 5*u^34 + 7*u^35 + u^36",
						"-1 + 27*u^2 + 225*u^3 - 827*u^4 + 658*u^5 - 5426*u^6 - 14846*u^7 - 3668*u^8 - 94362*u^9 + 16756*u^10 - 225234*u^11 + 20610*u^12 - 296886*u^13 - 19128*u^14 - 235594*u^15 - 55871*u^16 - 96214*u^17 - 43671*u^18 + 14539*u^19 - 3437*u^20 + 52090*u^21 + 22800*u^22 + 42140*u^23 + 24065*u^24 + 21952*u^25 + 14007*u^26 + 8335*u^27 + 5414*u^28 + 2324*u^29 + 1432*u^30 + 454*u^31 + 250*u^32 + 55*u^33 + 25*u^34 + 3*u^35 + u^36",
						"1 + 19*u + 177*u^2 + 1132*u^3 + 4859*u^4 + 6592*u^5 - 28302*u^6 + 126568*u^7 + 2046482*u^8 + 7010024*u^9 + 10646856*u^10 + 4865428*u^11 - 37205324*u^12 - 110140520*u^13 - 194492574*u^14 - 281544876*u^15 - 314989617*u^16 - 302275759*u^17 - 243723039*u^18 - 157569908*u^19 - 90211667*u^20 - 39464336*u^21 - 15862268*u^22 - 6422474*u^23 - 1781431*u^24 - 853269*u^25 - 108583*u^26 - 36222*u^27 - 33436*u^28 - 4465*u^29 + 6252*u^30 - 1220*u^31 - 377*u^32 + 152*u^33 - 9*u^34 - 6*u^35 + u^36",
						"1 + 1288*u + 16358*u^2 + 102720*u^3 + 433229*u^4 + 1385504*u^5 + 3573036*u^6 + 7701924*u^7 + 14207226*u^8 + 22824212*u^9 + 32403720*u^10 + 41180276*u^11 + 47401908*u^12 + 49968688*u^13 + 48735662*u^14 + 44384994*u^15 + 38025867*u^16 + 30785546*u^17 + 23573990*u^18 + 17035524*u^19 + 11582905*u^20 + 7416896*u^21 + 4520202*u^22 + 2684750*u^23 + 1600691*u^24 + 971050*u^25 + 587692*u^26 + 339942*u^27 + 180040*u^28 + 84500*u^29 + 34323*u^30 + 11819*u^31 + 3371*u^32 + 771*u^33 + 134*u^34 + 16*u^35 + u^36",
						"8 + 100*u + 444*u^2 + 1029*u^3 + 1905*u^4 + 3348*u^5 + 2886*u^6 - 1722*u^7 - 4088*u^8 - 2406*u^9 - 5698*u^10 - 9826*u^11 - 4082*u^12 + 12762*u^13 + 32088*u^14 + 20150*u^15 - 30706*u^16 - 51496*u^17 - 4890*u^18 + 41523*u^19 + 29459*u^20 - 9900*u^21 - 23648*u^22 - 7698*u^23 + 8010*u^24 + 7424*u^25 + 42*u^26 - 2697*u^27 - 1101*u^28 + 360*u^29 + 430*u^30 + 69*u^31 - 71*u^32 - 35*u^33 + 2*u^34 + 5*u^35 + u^36",
						"-31 - 106*u + 476*u^2 + 1976*u^3 - 127*u^4 + 2926*u^5 + 34000*u^6 - 59504*u^7 - 498278*u^8 - 337206*u^9 + 1738254*u^10 + 2599698*u^11 - 803112*u^12 - 2379022*u^13 - 1098742*u^14 - 4545416*u^15 - 204455*u^16 + 7092604*u^17 - 1337188*u^18 - 1508320*u^19 + 4814611*u^20 - 1361896*u^21 - 2925566*u^22 + 1839532*u^23 - 800287*u^24 - 762326*u^25 + 300522*u^26 + 5154*u^27 + 150914*u^28 + 15184*u^29 + 21983*u^30 + 1735*u^31 + 1597*u^32 + 55*u^33 + 64*u^34 + u^36",
						"41 - 185*u - 7*u^2 + 3302*u^3 - 2695*u^4 - 11788*u^5 + 23466*u^6 + 9188*u^7 - 52832*u^8 + 25426*u^9 + 34322*u^10 - 60198*u^11 - 12*u^12 - 6588*u^13 - 14674*u^14 + 34878*u^15 + 35155*u^16 + 13805*u^17 - 6055*u^18 - 23506*u^19 - 18527*u^20 + 9190*u^21 - 2364*u^22 - 4970*u^23 + 6141*u^24 + 2787*u^25 - 519*u^26 + 628*u^27 + 1028*u^28 + 235*u^29 + 190*u^30 + 22*u^31 + 49*u^32 + 4*u^33 + 13*u^34 + 2*u^35 + u^36",
						"-1 + 27*u^2 + 225*u^3 - 827*u^4 + 658*u^5 - 5426*u^6 - 14846*u^7 - 3668*u^8 - 94362*u^9 + 16756*u^10 - 225234*u^11 + 20610*u^12 - 296886*u^13 - 19128*u^14 - 235594*u^15 - 55871*u^16 - 96214*u^17 - 43671*u^18 + 14539*u^19 - 3437*u^20 + 52090*u^21 + 22800*u^22 + 42140*u^23 + 24065*u^24 + 21952*u^25 + 14007*u^26 + 8335*u^27 + 5414*u^28 + 2324*u^29 + 1432*u^30 + 454*u^31 + 250*u^32 + 55*u^33 + 25*u^34 + 3*u^35 + u^36",
						"-5351 + 95704*u + 172809*u^2 + 328493*u^3 + 1800513*u^4 - 950746*u^5 + 6740072*u^6 - 985454*u^7 + 1299904*u^8 + 14076080*u^9 - 34732254*u^10 + 18744538*u^11 - 5832470*u^12 + 25105558*u^13 - 6762276*u^14 + 9507018*u^15 - 10102109*u^16 + 931252*u^17 - 7627895*u^18 - 6302013*u^19 - 5716199*u^20 - 2378218*u^21 - 128220*u^22 + 69938*u^23 + 501343*u^24 + 95692*u^25 + 220319*u^26 + 12577*u^27 + 53270*u^28 + 614*u^29 + 7676*u^30 - 64*u^31 + 726*u^32 - 19*u^33 + 41*u^34 - u^35 + u^36",
						"-251 + 5421*u + 32649*u^2 - 138800*u^3 - 343635*u^4 + 1174176*u^5 + 1226510*u^6 - 2026256*u^7 - 7242368*u^8 + 4419262*u^9 + 5570024*u^10 + 5523192*u^11 + 9647522*u^12 + 11253126*u^13 + 3351024*u^14 - 14675836*u^15 - 17228045*u^16 - 10585085*u^17 + 175293*u^18 + 3498004*u^19 + 1339433*u^20 + 755528*u^21 + 769874*u^22 + 2063784*u^23 + 2220913*u^24 + 1732043*u^25 + 1107843*u^26 + 545972*u^27 + 259530*u^28 + 93899*u^29 + 33350*u^30 + 8558*u^31 + 2227*u^32 + 368*u^33 + 71*u^34 + 6*u^35 + u^36",
						"1 + 15*u + 103*u^2 + 562*u^3 + 2749*u^4 + 10884*u^5 + 37248*u^6 + 114320*u^7 + 325006*u^8 + 852306*u^9 + 1996286*u^10 + 4093736*u^11 + 7300912*u^12 + 11408466*u^13 + 15782560*u^14 + 19527536*u^15 + 21809731*u^16 + 22131115*u^17 + 20556345*u^18 + 17524202*u^19 + 13793905*u^20 + 10025362*u^21 + 6757844*u^22 + 4218456*u^23 + 2443643*u^24 + 1311487*u^25 + 650687*u^26 + 298466*u^27 + 125348*u^28 + 48389*u^29 + 16792*u^30 + 5286*u^31 + 1445*u^32 + 346*u^33 + 67*u^34 + 10*u^35 + u^36",
						"-17 + 95*u - 587*u^2 - 2282*u^3 + 27179*u^4 - 88204*u^5 + 141178*u^6 + 140876*u^7 - 890746*u^8 + 1971372*u^9 - 1652704*u^10 - 1815074*u^11 + 7148598*u^12 - 10124032*u^13 + 1128740*u^14 + 11174122*u^15 + 2154373*u^16 - 20583105*u^17 + 3854755*u^18 + 12558442*u^19 + 3692613*u^20 - 11805118*u^21 - 4006184*u^22 + 10733938*u^23 - 2056097*u^24 - 3246851*u^25 + 1523667*u^26 + 310490*u^27 - 333432*u^28 + 28269*u^29 + 29412*u^30 - 6926*u^31 - 887*u^32 + 430*u^33 - 11*u^34 - 10*u^35 + u^36",
						"-1 - u - 7*u^2 - 114*u^3 - 203*u^4 + 930*u^5 + 3056*u^6 - 3358*u^7 - 17518*u^8 + 24222*u^9 + 154418*u^10 - 15474*u^11 - 836328*u^12 - 381672*u^13 + 2858604*u^14 + 1867400*u^15 - 6552263*u^16 - 4544567*u^17 + 10428975*u^18 + 7339072*u^19 - 11898939*u^20 - 8338652*u^21 + 9762000*u^22 + 6867856*u^23 - 5686463*u^24 - 3884367*u^25 + 2155629*u^26 + 1438688*u^27 - 421182*u^28 - 281861*u^29 + 2660*u^30 + 19806*u^31 + 1837*u^32 - 498*u^33 - 71*u^34 + 6*u^35 + u^36",
						"-1 + u + 7*u^2 - 10*u^3 - 17*u^4 + 32*u^5 + 80*u^6 - 84*u^7 - 266*u^8 + 140*u^9 + 728*u^10 - 288*u^11 - 1430*u^12 + 720*u^13 + 1886*u^14 - 1162*u^15 - 2035*u^16 + 1527*u^17 + 1619*u^18 - 1386*u^19 - 1323*u^20 + 1356*u^21 + 608*u^22 - 806*u^23 - 395*u^24 + 573*u^25 + 93*u^26 - 248*u^27 - 46*u^28 + 129*u^29 - 6*u^30 - 40*u^31 + 5*u^32 + 12*u^33 - 3*u^34 - 2*u^35 + u^36",
						"-1 + u + 7*u^2 - 10*u^3 - 17*u^4 + 32*u^5 + 80*u^6 - 84*u^7 - 266*u^8 + 140*u^9 + 728*u^10 - 288*u^11 - 1430*u^12 + 720*u^13 + 1886*u^14 - 1162*u^15 - 2035*u^16 + 1527*u^17 + 1619*u^18 - 1386*u^19 - 1323*u^20 + 1356*u^21 + 608*u^22 - 806*u^23 - 395*u^24 + 573*u^25 + 93*u^26 - 248*u^27 - 46*u^28 + 129*u^29 - 6*u^30 - 40*u^31 + 5*u^32 + 12*u^33 - 3*u^34 - 2*u^35 + u^36",
						"-1 - u - 7*u^2 - 114*u^3 - 203*u^4 + 930*u^5 + 3056*u^6 - 3358*u^7 - 17518*u^8 + 24222*u^9 + 154418*u^10 - 15474*u^11 - 836328*u^12 - 381672*u^13 + 2858604*u^14 + 1867400*u^15 - 6552263*u^16 - 4544567*u^17 + 10428975*u^18 + 7339072*u^19 - 11898939*u^20 - 8338652*u^21 + 9762000*u^22 + 6867856*u^23 - 5686463*u^24 - 3884367*u^25 + 2155629*u^26 + 1438688*u^27 - 421182*u^28 - 281861*u^29 + 2660*u^30 + 19806*u^31 + 1837*u^32 - 498*u^33 - 71*u^34 + 6*u^35 + u^36",
						"-17 + 95*u - 587*u^2 - 2282*u^3 + 27179*u^4 - 88204*u^5 + 141178*u^6 + 140876*u^7 - 890746*u^8 + 1971372*u^9 - 1652704*u^10 - 1815074*u^11 + 7148598*u^12 - 10124032*u^13 + 1128740*u^14 + 11174122*u^15 + 2154373*u^16 - 20583105*u^17 + 3854755*u^18 + 12558442*u^19 + 3692613*u^20 - 11805118*u^21 - 4006184*u^22 + 10733938*u^23 - 2056097*u^24 - 3246851*u^25 + 1523667*u^26 + 310490*u^27 - 333432*u^28 + 28269*u^29 + 29412*u^30 - 6926*u^31 - 887*u^32 + 430*u^33 - 11*u^34 - 10*u^35 + u^36",
						"64 - 2896*u + 21816*u^2 + 9375*u^3 - 419399*u^4 + 90320*u^5 + 6075840*u^6 - 17601924*u^7 + 23487752*u^8 - 38317776*u^9 + 89612120*u^10 - 90317774*u^11 - 120533230*u^12 + 423965504*u^13 - 334553592*u^14 - 421624070*u^15 + 1415696546*u^16 - 1912395458*u^17 + 1648242588*u^18 - 987349683*u^19 + 420806267*u^20 - 140983764*u^21 + 62853048*u^22 - 49590926*u^23 + 36972062*u^24 - 20330974*u^25 + 8137700*u^26 - 2402807*u^27 + 552695*u^28 - 128834*u^29 + 44720*u^30 - 17971*u^31 + 5789*u^32 - 1339*u^33 + 212*u^34 - 21*u^35 + u^36",
						"1750247 + 3231841*u - 42179953*u^2 + 78786562*u^3 + 710407275*u^4 + 1487844*u^5 - 4950681812*u^6 - 13580484478*u^7 - 26833022718*u^8 - 42790176036*u^9 - 38579659740*u^10 - 3701865760*u^11 + 24756759370*u^12 + 29922445822*u^13 + 32362443252*u^14 + 19555703486*u^15 - 10525464221*u^16 - 14608219853*u^17 + 2600777745*u^18 + 3957769672*u^19 - 2677689629*u^20 - 1442049046*u^21 + 653763788*u^22 + 180607400*u^23 - 169014595*u^24 - 37965695*u^25 + 32003369*u^26 + 19896804*u^27 + 5604802*u^28 + 1044263*u^29 + 169048*u^30 + 34232*u^31 + 8037*u^32 + 1576*u^33 + 219*u^34 + 20*u^35 + u^36",
						"-29729 - 20527*u + 812279*u^2 + 702566*u^3 - 8068349*u^4 - 7087306*u^5 + 41424690*u^6 + 33813126*u^7 - 142817036*u^8 - 124175860*u^9 + 331137670*u^10 + 339466848*u^11 - 506502918*u^12 - 609676622*u^13 + 532147964*u^14 + 640767442*u^15 - 521250829*u^16 - 416707207*u^17 + 411377163*u^18 + 130905202*u^19 - 184614199*u^20 - 20177508*u^21 + 51400028*u^22 + 1862684*u^23 - 10875083*u^24 + 168117*u^25 + 1821821*u^26 - 151148*u^27 - 216030*u^28 + 30471*u^29 + 18136*u^30 - 3688*u^31 - 973*u^32 + 288*u^33 + 19*u^34 - 12*u^35 + u^36",
						"-1 + u + 7*u^2 - 10*u^3 - 17*u^4 + 32*u^5 + 80*u^6 - 84*u^7 - 266*u^8 + 140*u^9 + 728*u^10 - 288*u^11 - 1430*u^12 + 720*u^13 + 1886*u^14 - 1162*u^15 - 2035*u^16 + 1527*u^17 + 1619*u^18 - 1386*u^19 - 1323*u^20 + 1356*u^21 + 608*u^22 - 806*u^23 - 395*u^24 + 573*u^25 + 93*u^26 - 248*u^27 - 46*u^28 + 129*u^29 - 6*u^30 - 40*u^31 + 5*u^32 + 12*u^33 - 3*u^34 - 2*u^35 + u^36",
						"-2544983 + 38236385*u - 154635493*u^2 - 214324772*u^3 + 1955455711*u^4 - 653486658*u^5 - 9086519488*u^6 + 9190357036*u^7 + 19498331518*u^8 - 33606154968*u^9 - 7234452928*u^10 + 25855834288*u^11 + 20809602682*u^12 - 22275714630*u^13 - 15321570068*u^14 + 6489522440*u^15 + 4880224801*u^16 - 1829812365*u^17 - 2493163471*u^18 + 971265324*u^19 + 899442999*u^20 - 414462694*u^21 - 69190058*u^22 + 114078972*u^23 - 16074189*u^24 - 14076803*u^25 + 4188397*u^26 + 429726*u^27 - 233432*u^28 + 56423*u^29 - 9644*u^30 + 3736*u^31 + 357*u^32 - 74*u^33 + 21*u^34 - 2*u^35 + u^36",
						"2446750881 + 12016510299*u - 8719718769*u^2 - 98432135928*u^3 - 32396902083*u^4 + 118991839788*u^5 - 502500466680*u^6 - 1397722946718*u^7 - 1423202982046*u^8 - 1026749816124*u^9 - 916684242330*u^10 - 831519040800*u^11 - 427190655676*u^12 - 83782480738*u^13 - 7287082880*u^14 + 2393294194*u^15 + 31932376255*u^16 + 35790784749*u^17 + 17524623619*u^18 + 5339754222*u^19 + 1912382017*u^20 + 792082094*u^21 + 149186316*u^22 - 20375924*u^23 - 12370923*u^24 - 7637595*u^25 - 5437969*u^26 - 1639552*u^27 - 206992*u^28 - 37787*u^29 - 15092*u^30 - 824*u^31 + 731*u^32 + 98*u^33 + 13*u^34 + 6*u^35 + u^36",
						"1 + 15*u - 93*u^2 - 1042*u^3 + 3805*u^4 + 60924*u^5 + 207976*u^6 + 17792*u^7 - 1858806*u^8 - 5432326*u^9 - 2716598*u^10 + 23360924*u^11 + 74090292*u^12 + 90003450*u^13 - 45862144*u^14 - 382371744*u^15 - 716230605*u^16 - 579739005*u^17 + 444515861*u^18 + 2283432418*u^19 + 4255599869*u^20 + 5478620262*u^21 + 5472774652*u^22 + 4428307732*u^23 + 2959796263*u^24 + 1648956039*u^25 + 768122927*u^26 + 298887382*u^27 + 96726312*u^28 + 25832441*u^29 + 5626668*u^30 + 982566*u^31 + 134161*u^32 + 13790*u^33 + 1003*u^34 + 46*u^35 + u^36",
						"1359 + 12267*u - 31679*u^2 - 297418*u^3 + 635013*u^4 + 4109372*u^5 - 1341552*u^6 - 18128988*u^7 + 327286*u^8 + 43889870*u^9 + 1202802*u^10 - 68753616*u^11 + 1471504*u^12 + 75638450*u^13 - 8073796*u^14 - 61277134*u^15 + 12633901*u^16 + 37620957*u^17 - 11855371*u^18 - 17651922*u^19 + 7779429*u^20 + 6214090*u^21 - 3761376*u^22 - 1554822*u^23 + 1382221*u^24 + 213437*u^25 - 382529*u^26 + 20164*u^27 + 73926*u^28 - 19151*u^29 - 7364*u^30 + 4348*u^31 - 225*u^32 - 370*u^33 + 127*u^34 - 18*u^35 + u^36",
						"1 + 7*u + 17*u^2 + 20*u^3 - 51*u^4 - 238*u^5 - 78*u^6 + 464*u^7 + 416*u^8 + 556*u^9 - 18*u^10 - 3674*u^11 - 2562*u^12 + 5478*u^13 + 6374*u^14 + 1134*u^15 - 6461*u^16 - 18355*u^17 - 1011*u^18 + 36852*u^19 + 12199*u^20 - 43442*u^21 - 18546*u^22 + 34866*u^23 + 16363*u^24 - 19755*u^25 - 9649*u^26 + 7900*u^27 + 3922*u^28 - 2179*u^29 - 1088*u^30 + 394*u^31 + 197*u^32 - 42*u^33 - 21*u^34 + 2*u^35 + u^36",
						"1 + 7*u + 17*u^2 + 20*u^3 - 51*u^4 - 238*u^5 - 78*u^6 + 464*u^7 + 416*u^8 + 556*u^9 - 18*u^10 - 3674*u^11 - 2562*u^12 + 5478*u^13 + 6374*u^14 + 1134*u^15 - 6461*u^16 - 18355*u^17 - 1011*u^18 + 36852*u^19 + 12199*u^20 - 43442*u^21 - 18546*u^22 + 34866*u^23 + 16363*u^24 - 19755*u^25 - 9649*u^26 + 7900*u^27 + 3922*u^28 - 2179*u^29 - 1088*u^30 + 394*u^31 + 197*u^32 - 42*u^33 - 21*u^34 + 2*u^35 + u^36",
						"-119 - 565*u + 1893*u^2 + 12244*u^3 + 9165*u^4 - 48108*u^5 - 174282*u^6 - 5150*u^7 + 1315022*u^8 + 1675316*u^9 - 1703448*u^10 - 2607674*u^11 + 310392*u^12 + 1150918*u^13 + 1075374*u^14 + 4811862*u^15 + 4230519*u^16 - 3751559*u^17 - 1999931*u^18 + 4620578*u^19 + 4856473*u^20 + 3724442*u^21 - 2425188*u^22 - 5022472*u^23 + 684463*u^24 + 2154951*u^25 - 176563*u^26 - 498078*u^27 + 42074*u^28 + 69371*u^29 - 7090*u^30 - 5874*u^31 + 727*u^32 + 282*u^33 - 41*u^34 - 6*u^35 + u^36",
						"-119 - 565*u + 1893*u^2 + 12244*u^3 + 9165*u^4 - 48108*u^5 - 174282*u^6 - 5150*u^7 + 1315022*u^8 + 1675316*u^9 - 1703448*u^10 - 2607674*u^11 + 310392*u^12 + 1150918*u^13 + 1075374*u^14 + 4811862*u^15 + 4230519*u^16 - 3751559*u^17 - 1999931*u^18 + 4620578*u^19 + 4856473*u^20 + 3724442*u^21 - 2425188*u^22 - 5022472*u^23 + 684463*u^24 + 2154951*u^25 - 176563*u^26 - 498078*u^27 + 42074*u^28 + 69371*u^29 - 7090*u^30 - 5874*u^31 + 727*u^32 + 282*u^33 - 41*u^34 - 6*u^35 + u^36",
						"1 + 7*u + 17*u^2 + 20*u^3 - 51*u^4 - 238*u^5 - 78*u^6 + 464*u^7 + 416*u^8 + 556*u^9 - 18*u^10 - 3674*u^11 - 2562*u^12 + 5478*u^13 + 6374*u^14 + 1134*u^15 - 6461*u^16 - 18355*u^17 - 1011*u^18 + 36852*u^19 + 12199*u^20 - 43442*u^21 - 18546*u^22 + 34866*u^23 + 16363*u^24 - 19755*u^25 - 9649*u^26 + 7900*u^27 + 3922*u^28 - 2179*u^29 - 1088*u^30 + 394*u^31 + 197*u^32 - 42*u^33 - 21*u^34 + 2*u^35 + u^36",
						"1 + 15*u + 103*u^2 + 562*u^3 + 2749*u^4 + 10884*u^5 + 37248*u^6 + 114320*u^7 + 325006*u^8 + 852306*u^9 + 1996286*u^10 + 4093736*u^11 + 7300912*u^12 + 11408466*u^13 + 15782560*u^14 + 19527536*u^15 + 21809731*u^16 + 22131115*u^17 + 20556345*u^18 + 17524202*u^19 + 13793905*u^20 + 10025362*u^21 + 6757844*u^22 + 4218456*u^23 + 2443643*u^24 + 1311487*u^25 + 650687*u^26 + 298466*u^27 + 125348*u^28 + 48389*u^29 + 16792*u^30 + 5286*u^31 + 1445*u^32 + 346*u^33 + 67*u^34 + 10*u^35 + u^36",
						"-119 - 565*u + 1893*u^2 + 12244*u^3 + 9165*u^4 - 48108*u^5 - 174282*u^6 - 5150*u^7 + 1315022*u^8 + 1675316*u^9 - 1703448*u^10 - 2607674*u^11 + 310392*u^12 + 1150918*u^13 + 1075374*u^14 + 4811862*u^15 + 4230519*u^16 - 3751559*u^17 - 1999931*u^18 + 4620578*u^19 + 4856473*u^20 + 3724442*u^21 - 2425188*u^22 - 5022472*u^23 + 684463*u^24 + 2154951*u^25 - 176563*u^26 - 498078*u^27 + 42074*u^28 + 69371*u^29 - 7090*u^30 - 5874*u^31 + 727*u^32 + 282*u^33 - 41*u^34 - 6*u^35 + u^36",
						"1 + 7*u + 17*u^2 + 20*u^3 - 51*u^4 - 238*u^5 - 78*u^6 + 464*u^7 + 416*u^8 + 556*u^9 - 18*u^10 - 3674*u^11 - 2562*u^12 + 5478*u^13 + 6374*u^14 + 1134*u^15 - 6461*u^16 - 18355*u^17 - 1011*u^18 + 36852*u^19 + 12199*u^20 - 43442*u^21 - 18546*u^22 + 34866*u^23 + 16363*u^24 - 19755*u^25 - 9649*u^26 + 7900*u^27 + 3922*u^28 - 2179*u^29 - 1088*u^30 + 394*u^31 + 197*u^32 - 42*u^33 - 21*u^34 + 2*u^35 + u^36",
						"1 + 15*u - 93*u^2 - 1042*u^3 + 3805*u^4 + 60924*u^5 + 207976*u^6 + 17792*u^7 - 1858806*u^8 - 5432326*u^9 - 2716598*u^10 + 23360924*u^11 + 74090292*u^12 + 90003450*u^13 - 45862144*u^14 - 382371744*u^15 - 716230605*u^16 - 579739005*u^17 + 444515861*u^18 + 2283432418*u^19 + 4255599869*u^20 + 5478620262*u^21 + 5472774652*u^22 + 4428307732*u^23 + 2959796263*u^24 + 1648956039*u^25 + 768122927*u^26 + 298887382*u^27 + 96726312*u^28 + 25832441*u^29 + 5626668*u^30 + 982566*u^31 + 134161*u^32 + 13790*u^33 + 1003*u^34 + 46*u^35 + u^36",
						"1359 + 12267*u - 31679*u^2 - 297418*u^3 + 635013*u^4 + 4109372*u^5 - 1341552*u^6 - 18128988*u^7 + 327286*u^8 + 43889870*u^9 + 1202802*u^10 - 68753616*u^11 + 1471504*u^12 + 75638450*u^13 - 8073796*u^14 - 61277134*u^15 + 12633901*u^16 + 37620957*u^17 - 11855371*u^18 - 17651922*u^19 + 7779429*u^20 + 6214090*u^21 - 3761376*u^22 - 1554822*u^23 + 1382221*u^24 + 213437*u^25 - 382529*u^26 + 20164*u^27 + 73926*u^28 - 19151*u^29 - 7364*u^30 + 4348*u^31 - 225*u^32 - 370*u^33 + 127*u^34 - 18*u^35 + u^36",
						"1 + 15*u - 93*u^2 - 1042*u^3 + 3805*u^4 + 60924*u^5 + 207976*u^6 + 17792*u^7 - 1858806*u^8 - 5432326*u^9 - 2716598*u^10 + 23360924*u^11 + 74090292*u^12 + 90003450*u^13 - 45862144*u^14 - 382371744*u^15 - 716230605*u^16 - 579739005*u^17 + 444515861*u^18 + 2283432418*u^19 + 4255599869*u^20 + 5478620262*u^21 + 5472774652*u^22 + 4428307732*u^23 + 2959796263*u^24 + 1648956039*u^25 + 768122927*u^26 + 298887382*u^27 + 96726312*u^28 + 25832441*u^29 + 5626668*u^30 + 982566*u^31 + 134161*u^32 + 13790*u^33 + 1003*u^34 + 46*u^35 + u^36"
					],
					"uPolysN":[
						"-1 + 40*u - 156*u^2 + 84*u^3 + 629*u^4 - 1248*u^5 - 372*u^6 + 3676*u^7 - 2970*u^8 - 4364*u^9 + 9108*u^10 - 1004*u^11 - 11920*u^12 + 10496*u^13 + 5990*u^14 - 15262*u^15 + 4429*u^16 + 10802*u^17 - 10236*u^18 - 2376*u^19 + 8693*u^20 - 3040*u^21 - 3934*u^22 + 3766*u^23 + 365*u^24 - 2110*u^25 + 758*u^26 + 618*u^27 - 550*u^28 - 36*u^29 + 207*u^30 - 57*u^31 - 41*u^32 + 27*u^33 - 4*u^35 + u^36",
						"1 - 1288*u + 16358*u^2 - 102720*u^3 + 433229*u^4 - 1385504*u^5 + 3573036*u^6 - 7701924*u^7 + 14207226*u^8 - 22824212*u^9 + 32403720*u^10 - 41180276*u^11 + 47401908*u^12 - 49968688*u^13 + 48735662*u^14 - 44384994*u^15 + 38025867*u^16 - 30785546*u^17 + 23573990*u^18 - 17035524*u^19 + 11582905*u^20 - 7416896*u^21 + 4520202*u^22 - 2684750*u^23 + 1600691*u^24 - 971050*u^25 + 587692*u^26 - 339942*u^27 + 180040*u^28 - 84500*u^29 + 34323*u^30 - 11819*u^31 + 3371*u^32 - 771*u^33 + 134*u^34 - 16*u^35 + u^36",
						"8 + 100*u + 444*u^2 + 1029*u^3 + 1905*u^4 + 3348*u^5 + 2886*u^6 - 1722*u^7 - 4088*u^8 - 2406*u^9 - 5698*u^10 - 9826*u^11 - 4082*u^12 + 12762*u^13 + 32088*u^14 + 20150*u^15 - 30706*u^16 - 51496*u^17 - 4890*u^18 + 41523*u^19 + 29459*u^20 - 9900*u^21 - 23648*u^22 - 7698*u^23 + 8010*u^24 + 7424*u^25 + 42*u^26 - 2697*u^27 - 1101*u^28 + 360*u^29 + 430*u^30 + 69*u^31 - 71*u^32 - 35*u^33 + 2*u^34 + 5*u^35 + u^36",
						"1 + 40*u + 156*u^2 + 84*u^3 - 629*u^4 - 1248*u^5 + 372*u^6 + 3676*u^7 + 2970*u^8 - 4364*u^9 - 9108*u^10 - 1004*u^11 + 11920*u^12 + 10496*u^13 - 5990*u^14 - 15262*u^15 - 4429*u^16 + 10802*u^17 + 10236*u^18 - 2376*u^19 - 8693*u^20 - 3040*u^21 + 3934*u^22 + 3766*u^23 - 365*u^24 - 2110*u^25 - 758*u^26 + 618*u^27 + 550*u^28 - 36*u^29 - 207*u^30 - 57*u^31 + 41*u^32 + 27*u^33 - 4*u^35 - u^36",
						"-1 + u + 7*u^2 - 10*u^3 - 17*u^4 + 32*u^5 + 80*u^6 - 84*u^7 - 266*u^8 + 140*u^9 + 728*u^10 - 288*u^11 - 1430*u^12 + 720*u^13 + 1886*u^14 - 1162*u^15 - 2035*u^16 + 1527*u^17 + 1619*u^18 - 1386*u^19 - 1323*u^20 + 1356*u^21 + 608*u^22 - 806*u^23 - 395*u^24 + 573*u^25 + 93*u^26 - 248*u^27 - 46*u^28 + 129*u^29 - 6*u^30 - 40*u^31 + 5*u^32 + 12*u^33 - 3*u^34 - 2*u^35 + u^36",
						"8 - 100*u + 444*u^2 - 1029*u^3 + 1905*u^4 - 3348*u^5 + 2886*u^6 + 1722*u^7 - 4088*u^8 + 2406*u^9 - 5698*u^10 + 9826*u^11 - 4082*u^12 - 12762*u^13 + 32088*u^14 - 20150*u^15 - 30706*u^16 + 51496*u^17 - 4890*u^18 - 41523*u^19 + 29459*u^20 + 9900*u^21 - 23648*u^22 + 7698*u^23 + 8010*u^24 - 7424*u^25 + 42*u^26 + 2697*u^27 - 1101*u^28 - 360*u^29 + 430*u^30 - 69*u^31 - 71*u^32 + 35*u^33 + 2*u^34 - 5*u^35 + u^36",
						"1 + 7*u + 17*u^2 + 20*u^3 - 51*u^4 - 238*u^5 - 78*u^6 + 464*u^7 + 416*u^8 + 556*u^9 - 18*u^10 - 3674*u^11 - 2562*u^12 + 5478*u^13 + 6374*u^14 + 1134*u^15 - 6461*u^16 - 18355*u^17 - 1011*u^18 + 36852*u^19 + 12199*u^20 - 43442*u^21 - 18546*u^22 + 34866*u^23 + 16363*u^24 - 19755*u^25 - 9649*u^26 + 7900*u^27 + 3922*u^28 - 2179*u^29 - 1088*u^30 + 394*u^31 + 197*u^32 - 42*u^33 - 21*u^34 + 2*u^35 + u^36",
						"1 + 7*u + 17*u^2 + 20*u^3 - 51*u^4 - 238*u^5 - 78*u^6 + 464*u^7 + 416*u^8 + 556*u^9 - 18*u^10 - 3674*u^11 - 2562*u^12 + 5478*u^13 + 6374*u^14 + 1134*u^15 - 6461*u^16 - 18355*u^17 - 1011*u^18 + 36852*u^19 + 12199*u^20 - 43442*u^21 - 18546*u^22 + 34866*u^23 + 16363*u^24 - 19755*u^25 - 9649*u^26 + 7900*u^27 + 3922*u^28 - 2179*u^29 - 1088*u^30 + 394*u^31 + 197*u^32 - 42*u^33 - 21*u^34 + 2*u^35 + u^36",
						"1 + u - 7*u^2 - 10*u^3 + 17*u^4 + 32*u^5 - 80*u^6 - 84*u^7 + 266*u^8 + 140*u^9 - 728*u^10 - 288*u^11 + 1430*u^12 + 720*u^13 - 1886*u^14 - 1162*u^15 + 2035*u^16 + 1527*u^17 - 1619*u^18 - 1386*u^19 + 1323*u^20 + 1356*u^21 - 608*u^22 - 806*u^23 + 395*u^24 + 573*u^25 - 93*u^26 - 248*u^27 + 46*u^28 + 129*u^29 + 6*u^30 - 40*u^31 - 5*u^32 + 12*u^33 + 3*u^34 - 2*u^35 - u^36",
						"1 - 7*u + 17*u^2 - 20*u^3 - 51*u^4 + 238*u^5 - 78*u^6 - 464*u^7 + 416*u^8 - 556*u^9 - 18*u^10 + 3674*u^11 - 2562*u^12 - 5478*u^13 + 6374*u^14 - 1134*u^15 - 6461*u^16 + 18355*u^17 - 1011*u^18 - 36852*u^19 + 12199*u^20 + 43442*u^21 - 18546*u^22 - 34866*u^23 + 16363*u^24 + 19755*u^25 - 9649*u^26 - 7900*u^27 + 3922*u^28 + 2179*u^29 - 1088*u^30 - 394*u^31 + 197*u^32 + 42*u^33 - 21*u^34 - 2*u^35 + u^36",
						"1 - 7*u + 17*u^2 - 20*u^3 - 51*u^4 + 238*u^5 - 78*u^6 - 464*u^7 + 416*u^8 - 556*u^9 - 18*u^10 + 3674*u^11 - 2562*u^12 - 5478*u^13 + 6374*u^14 - 1134*u^15 - 6461*u^16 + 18355*u^17 - 1011*u^18 - 36852*u^19 + 12199*u^20 + 43442*u^21 - 18546*u^22 - 34866*u^23 + 16363*u^24 + 19755*u^25 - 9649*u^26 - 7900*u^27 + 3922*u^28 + 2179*u^29 - 1088*u^30 - 394*u^31 + 197*u^32 + 42*u^33 - 21*u^34 - 2*u^35 + u^36",
						"1 - 7*u + 17*u^2 - 20*u^3 - 51*u^4 + 238*u^5 - 78*u^6 - 464*u^7 + 416*u^8 - 556*u^9 - 18*u^10 + 3674*u^11 - 2562*u^12 - 5478*u^13 + 6374*u^14 - 1134*u^15 - 6461*u^16 + 18355*u^17 - 1011*u^18 - 36852*u^19 + 12199*u^20 + 43442*u^21 - 18546*u^22 - 34866*u^23 + 16363*u^24 + 19755*u^25 - 9649*u^26 - 7900*u^27 + 3922*u^28 + 2179*u^29 - 1088*u^30 - 394*u^31 + 197*u^32 + 42*u^33 - 21*u^34 - 2*u^35 + u^36"
					]
				},
				{
					"IdealName":"J12n114_1",
					"Generators":[
						"1 + u",
						"1 - 2*a - a^2 + a^3",
						"2 - a^2 + b"
					],
					"VariableOrder":[
						"u",
						"a",
						"b"
					],
					"Characteristic":0,
					"KnownGroebner":[],
					"Status":[
						"vCompNormalize"
					],
					"MonomialOrder":"lex",
					"IsHomogeneous":false,
					"IsZeroDim":true,
					"IdealDimension":0,
					"ZeroDimensionalVars":[
						"u",
						"a",
						"b"
					],
					"Timings":{
						"TimingmagmaVCompNormalize":4.89e-4,
						"TimingComplexVolumeN":0.404356,
						"TimingObstruction":1.346e-3,
						"TiminguValues_ij":3.546e-3,
						"TiminguPolys_ij_N":1.0511e-2
					},
					"ComplexVolumeN":[
						-7.9896797532628141200088736665664080619206138058615924118584256855114648562441185300490546601531137114765924063884949261582,
						-2.3499058097831806235320216666371788417413570017239977681936546133857249577188583911908984294567981504342918842319102723995,
						-19.269227640222081112962577666424866502279127414136781699187967829762944653294638807765367121545744833561193450702
					],
					"GeometricComponent":0,
					"SortedReprnIndices":"{3, 1, 2}",
					"Abelian":false,
					"Obstruction":1,
					"ij_list":[
						[
							"{1, 2}"
						],
						[
							"{1, 3}"
						],
						[
							"{1, 4}"
						],
						[
							"{1, 5}"
						],
						[
							"{1, 6}"
						],
						[
							"{1, 7}"
						],
						[
							"{1, 8}"
						],
						[
							"{1, 9}"
						],
						[
							"{1, 10}"
						],
						[
							"{1, 11}"
						],
						[
							"{1, 12}"
						],
						[
							"{2, 3}"
						],
						[
							"{2, 4}"
						],
						[
							"{2, 5}"
						],
						[
							"{2, 6}"
						],
						[
							"{2, 7}"
						],
						[
							"{2, 8}"
						],
						[
							"{2, 9}"
						],
						[
							"{2, 10}"
						],
						[
							"{2, 11}"
						],
						[
							"{2, 12}"
						],
						[
							"{3, 4}"
						],
						[
							"{3, 5}"
						],
						[
							"{3, 6}"
						],
						[
							"{3, 7}"
						],
						[
							"{3, 8}"
						],
						[
							"{3, 9}"
						],
						[
							"{3, 10}"
						],
						[
							"{3, 11}"
						],
						[
							"{3, 12}"
						],
						[
							"{4, 5}"
						],
						[
							"{4, 6}",
							"{4, 7}"
						],
						[
							"{4, 8}"
						],
						[
							"{4, 9}"
						],
						[
							"{4, 10}"
						],
						[
							"{4, 11}"
						],
						[
							"{4, 12}"
						],
						[
							"{5, 6}"
						],
						[
							"{5, 7}"
						],
						[
							"{5, 8}"
						],
						[
							"{5, 9}"
						],
						[
							"{5, 10}"
						],
						[
							"{5, 11}"
						],
						[
							"{5, 12}"
						],
						[
							"{6, 7}"
						],
						[
							"{6, 8}"
						],
						[
							"{6, 9}"
						],
						[
							"{6, 10}"
						],
						[
							"{6, 11}"
						],
						[
							"{6, 12}"
						],
						[
							"{7, 8}",
							"{8, 9}"
						],
						[
							"{7, 9}"
						],
						[
							"{7, 10}"
						],
						[
							"{7, 11}"
						],
						[
							"{7, 12}"
						],
						[
							"{8, 10}"
						],
						[
							"{8, 11}",
							"{8, 12}"
						],
						[
							"{9, 10}"
						],
						[
							"{9, 11}"
						],
						[
							"{9, 12}"
						],
						[
							"{10, 11}"
						],
						[
							"{10, 12}"
						],
						[
							"{11, 12}"
						]
					],
					"uPolys_ij_N":[
						"-1 + 3*u - 3*u^2 + u^3",
						"-1 + 3*u - 3*u^2 + u^3",
						"-1 + 3*u - 3*u^2 + u^3",
						"u^3",
						"1 + 6*u + 5*u^2 + u^3",
						"1 + 6*u + 5*u^2 + u^3",
						"-1 - 4*u - 3*u^2 + u^3",
						"-1 - 2*u + u^2 + u^3",
						"-1 - 2*u + u^2 + u^3",
						"-1 - 4*u - 3*u^2 + u^3",
						"1 + 6*u + 5*u^2 + u^3",
						"-1 + 3*u - 3*u^2 + u^3",
						"-1 + 3*u - 3*u^2 + u^3",
						"-1 + 3*u - 3*u^2 + u^3",
						"1 + 6*u + 5*u^2 + u^3",
						"1 + 6*u + 5*u^2 + u^3",
						"-7 - 7*u + u^3",
						"-1 - u + 2*u^2 + u^3",
						"-13 - 4*u + 3*u^2 + u^3",
						"1 - 9*u - u^2 + u^3",
						"8 + 12*u + 6*u^2 + u^3",
						"u^3",
						"-1 + 3*u - 3*u^2 + u^3",
						"u^3",
						"u^3",
						"1 + 3*u + 3*u^2 + u^3",
						"-1 - 2*u + u^2 + u^3",
						"-1 - u + 2*u^2 + u^3",
						"-1 - u + 2*u^2 + u^3",
						"-1 - 2*u + u^2 + u^3",
						"-1 + 3*u - 3*u^2 + u^3",
						"u^3",
						"1 + 3*u + 3*u^2 + u^3",
						"-1 - 2*u + u^2 + u^3",
						"-1 - u + 2*u^2 + u^3",
						"-1 - u + 2*u^2 + u^3",
						"-1 - 2*u + u^2 + u^3",
						"-1 + 6*u - 5*u^2 + u^3",
						"-1 + 6*u - 5*u^2 + u^3",
						"1 - 4*u + 3*u^2 + u^3",
						"1 - 2*u - u^2 + u^3",
						"1 - 2*u - u^2 + u^3",
						"1 - 4*u + 3*u^2 + u^3",
						"-1 + 6*u - 5*u^2 + u^3",
						"u^3",
						"-1 + 6*u - 5*u^2 + u^3",
						"1 - 4*u + 3*u^2 + u^3",
						"1 - 2*u - u^2 + u^3",
						"1 - 2*u - u^2 + u^3",
						"1 - 4*u + 3*u^2 + u^3",
						"-1 + 6*u - 5*u^2 + u^3",
						"1 - 4*u + 3*u^2 + u^3",
						"1 - 2*u - u^2 + u^3",
						"1 - 2*u - u^2 + u^3",
						"1 - 4*u + 3*u^2 + u^3",
						"1 - 4*u + 3*u^2 + u^3",
						"1 - 2*u - u^2 + u^3",
						"-1 + 6*u - 5*u^2 + u^3",
						"1 - 4*u + 3*u^2 + u^3",
						"1 - 2*u - u^2 + u^3",
						"-1 + 6*u - 5*u^2 + u^3",
						"1 - 4*u + 3*u^2 + u^3",
						"-1 + 6*u - 5*u^2 + u^3"
					],
					"uPolysN":[
						"-1 + 3*u - 3*u^2 + u^3",
						"1 + 3*u + 3*u^2 + u^3",
						"u^3",
						"1 + 3*u + 3*u^2 + u^3",
						"1 - 2*u - u^2 + u^3",
						"-u^3",
						"1 - 2*u - u^2 + u^3",
						"1 - 2*u - u^2 + u^3",
						"1 + 2*u - u^2 - u^3",
						"1 + 2*u - u^2 - u^3",
						"1 + 2*u - u^2 - u^3",
						"1 + 2*u - u^2 - u^3"
					]
				},
				{
					"IdealName":"abJ12n114_2",
					"Generators":[
						"-1 + v",
						"-1 + a",
						"b"
					],
					"VariableOrder":[
						"v",
						"a",
						"b"
					],
					"Characteristic":0,
					"KnownGroebner":[],
					"Status":[
						"vCompNormalize"
					],
					"MonomialOrder":"lex",
					"IsHomogeneous":false,
					"IsZeroDim":true,
					"IdealDimension":0,
					"ZeroDimensionalVars":[
						"v",
						"a",
						"b"
					],
					"Timings":{
						"TimingmagmaVCompNormalize":4.94e-4,
						"TimingComplexVolumeN":0.113668,
						"TimingObstruction":3.56e-4,
						"TiminguValues_ij":3.25e-3,
						"TiminguPolys_ij_N":4.363e-3
					},
					"ComplexVolumeN":"{0}",
					"GeometricComponent":0,
					"SortedReprnIndices":"{1}",
					"Abelian":true,
					"Obstruction":1,
					"ij_list":[
						[
							"{1, 2}"
						],
						[
							"{1, 3}"
						],
						[
							"{1, 4}"
						],
						[
							"{1, 5}"
						],
						[
							"{1, 6}"
						],
						[
							"{1, 7}"
						],
						[
							"{1, 8}"
						],
						[
							"{1, 9}"
						],
						[
							"{1, 10}"
						],
						[
							"{1, 11}"
						],
						[
							"{1, 12}"
						],
						[
							"{2, 3}"
						],
						[
							"{2, 4}"
						],
						[
							"{2, 5}"
						],
						[
							"{2, 6}"
						],
						[
							"{2, 7}"
						],
						[
							"{2, 8}"
						],
						[
							"{2, 9}"
						],
						[
							"{2, 10}"
						],
						[
							"{2, 11}"
						],
						[
							"{2, 12}"
						],
						[
							"{3, 4}"
						],
						[
							"{3, 5}"
						],
						[
							"{3, 6}"
						],
						[
							"{3, 7}"
						],
						[
							"{3, 8}"
						],
						[
							"{3, 9}"
						],
						[
							"{3, 10}"
						],
						[
							"{3, 11}"
						],
						[
							"{3, 12}"
						],
						[
							"{4, 5}"
						],
						[
							"{4, 6}",
							"{4, 7}"
						],
						[
							"{4, 8}"
						],
						[
							"{4, 9}"
						],
						[
							"{4, 10}"
						],
						[
							"{4, 11}",
							"{4, 12}"
						],
						[
							"{5, 6}"
						],
						[
							"{5, 7}"
						],
						[
							"{5, 8}"
						],
						[
							"{5, 9}"
						],
						[
							"{5, 10}"
						],
						[
							"{5, 11}"
						],
						[
							"{5, 12}"
						],
						[
							"{6, 7}"
						],
						[
							"{6, 8}",
							"{7, 8}",
							"{8, 9}"
						],
						[
							"{6, 9}"
						],
						[
							"{6, 10}"
						],
						[
							"{6, 11}"
						],
						[
							"{6, 12}"
						],
						[
							"{7, 9}"
						],
						[
							"{7, 10}"
						],
						[
							"{7, 11}"
						],
						[
							"{7, 12}"
						],
						[
							"{8, 10}"
						],
						[
							"{8, 11}",
							"{8, 12}"
						],
						[
							"{9, 10}"
						],
						[
							"{9, 11}"
						],
						[
							"{9, 12}"
						],
						[
							"{10, 11}"
						],
						[
							"{10, 12}"
						],
						[
							"{11, 12}"
						]
					],
					"uPolys_ij_N":[
						"u",
						"u",
						"u",
						"u",
						"u",
						"u",
						"u",
						"u",
						"u",
						"u",
						"u",
						"u",
						"u",
						"u",
						"u",
						"u",
						"u",
						"u",
						"u",
						"u",
						"u",
						"u",
						"u",
						"u",
						"u",
						"u",
						"u",
						"u",
						"u",
						"u",
						"u",
						"u",
						"u",
						"u",
						"u",
						"u",
						"u",
						"u",
						"u",
						"u",
						"u",
						"u",
						"u",
						"u",
						"u",
						"u",
						"u",
						"u",
						"u",
						"u",
						"u",
						"u",
						"u",
						"u",
						"u",
						"u",
						"u",
						"u",
						"u",
						"u",
						"u"
					],
					"uPolysN":[
						"u",
						"-u",
						"u",
						"-u",
						"u",
						"-u",
						"u",
						"u",
						"-u",
						"-u",
						"-u",
						"-u"
					]
				}
			],
			"uPolyC":[
				"(-1 + 3*u - 3*u^2 + u^3)*(-1 + 40*u - 156*u^2 + 84*u^3 + 629*u^4 - 1248*u^5 - 372*u^6 + 3676*u^7 - 2970*u^8 - 4364*u^9 + 9108*u^10 - 1004*u^11 - 11920*u^12 + 10496*u^13 + 5990*u^14 - 15262*u^15 + 4429*u^16 + 10802*u^17 - 10236*u^18 - 2376*u^19 + 8693*u^20 - 3040*u^21 - 3934*u^22 + 3766*u^23 + 365*u^24 - 2110*u^25 + 758*u^26 + 618*u^27 - 550*u^28 - 36*u^29 + 207*u^30 - 57*u^31 - 41*u^32 + 27*u^33 - 4*u^35 + u^36)",
				"(1 + 3*u + 3*u^2 + u^3)*(1 - 1288*u + 16358*u^2 - 102720*u^3 + 433229*u^4 - 1385504*u^5 + 3573036*u^6 - 7701924*u^7 + 14207226*u^8 - 22824212*u^9 + 32403720*u^10 - 41180276*u^11 + 47401908*u^12 - 49968688*u^13 + 48735662*u^14 - 44384994*u^15 + 38025867*u^16 - 30785546*u^17 + 23573990*u^18 - 17035524*u^19 + 11582905*u^20 - 7416896*u^21 + 4520202*u^22 - 2684750*u^23 + 1600691*u^24 - 971050*u^25 + 587692*u^26 - 339942*u^27 + 180040*u^28 - 84500*u^29 + 34323*u^30 - 11819*u^31 + 3371*u^32 - 771*u^33 + 134*u^34 - 16*u^35 + u^36)",
				"u^3*(8 + 100*u + 444*u^2 + 1029*u^3 + 1905*u^4 + 3348*u^5 + 2886*u^6 - 1722*u^7 - 4088*u^8 - 2406*u^9 - 5698*u^10 - 9826*u^11 - 4082*u^12 + 12762*u^13 + 32088*u^14 + 20150*u^15 - 30706*u^16 - 51496*u^17 - 4890*u^18 + 41523*u^19 + 29459*u^20 - 9900*u^21 - 23648*u^22 - 7698*u^23 + 8010*u^24 + 7424*u^25 + 42*u^26 - 2697*u^27 - 1101*u^28 + 360*u^29 + 430*u^30 + 69*u^31 - 71*u^32 - 35*u^33 + 2*u^34 + 5*u^35 + u^36)",
				"(1 + 3*u + 3*u^2 + u^3)*(1 + 40*u + 156*u^2 + 84*u^3 - 629*u^4 - 1248*u^5 + 372*u^6 + 3676*u^7 + 2970*u^8 - 4364*u^9 - 9108*u^10 - 1004*u^11 + 11920*u^12 + 10496*u^13 - 5990*u^14 - 15262*u^15 - 4429*u^16 + 10802*u^17 + 10236*u^18 - 2376*u^19 - 8693*u^20 - 3040*u^21 + 3934*u^22 + 3766*u^23 - 365*u^24 - 2110*u^25 - 758*u^26 + 618*u^27 + 550*u^28 - 36*u^29 - 207*u^30 - 57*u^31 + 41*u^32 + 27*u^33 - 4*u^35 - u^36)",
				"(1 - 2*u - u^2 + u^3)*(-1 + u + 7*u^2 - 10*u^3 - 17*u^4 + 32*u^5 + 80*u^6 - 84*u^7 - 266*u^8 + 140*u^9 + 728*u^10 - 288*u^11 - 1430*u^12 + 720*u^13 + 1886*u^14 - 1162*u^15 - 2035*u^16 + 1527*u^17 + 1619*u^18 - 1386*u^19 - 1323*u^20 + 1356*u^21 + 608*u^22 - 806*u^23 - 395*u^24 + 573*u^25 + 93*u^26 - 248*u^27 - 46*u^28 + 129*u^29 - 6*u^30 - 40*u^31 + 5*u^32 + 12*u^33 - 3*u^34 - 2*u^35 + u^36)",
				"-(u^3*(8 - 100*u + 444*u^2 - 1029*u^3 + 1905*u^4 - 3348*u^5 + 2886*u^6 + 1722*u^7 - 4088*u^8 + 2406*u^9 - 5698*u^10 + 9826*u^11 - 4082*u^12 - 12762*u^13 + 32088*u^14 - 20150*u^15 - 30706*u^16 + 51496*u^17 - 4890*u^18 - 41523*u^19 + 29459*u^20 + 9900*u^21 - 23648*u^22 + 7698*u^23 + 8010*u^24 - 7424*u^25 + 42*u^26 + 2697*u^27 - 1101*u^28 - 360*u^29 + 430*u^30 - 69*u^31 - 71*u^32 + 35*u^33 + 2*u^34 - 5*u^35 + u^36))",
				"(1 - 2*u - u^2 + u^3)*(1 + 7*u + 17*u^2 + 20*u^3 - 51*u^4 - 238*u^5 - 78*u^6 + 464*u^7 + 416*u^8 + 556*u^9 - 18*u^10 - 3674*u^11 - 2562*u^12 + 5478*u^13 + 6374*u^14 + 1134*u^15 - 6461*u^16 - 18355*u^17 - 1011*u^18 + 36852*u^19 + 12199*u^20 - 43442*u^21 - 18546*u^22 + 34866*u^23 + 16363*u^24 - 19755*u^25 - 9649*u^26 + 7900*u^27 + 3922*u^28 - 2179*u^29 - 1088*u^30 + 394*u^31 + 197*u^32 - 42*u^33 - 21*u^34 + 2*u^35 + u^36)",
				"(1 - 2*u - u^2 + u^3)*(1 + 7*u + 17*u^2 + 20*u^3 - 51*u^4 - 238*u^5 - 78*u^6 + 464*u^7 + 416*u^8 + 556*u^9 - 18*u^10 - 3674*u^11 - 2562*u^12 + 5478*u^13 + 6374*u^14 + 1134*u^15 - 6461*u^16 - 18355*u^17 - 1011*u^18 + 36852*u^19 + 12199*u^20 - 43442*u^21 - 18546*u^22 + 34866*u^23 + 16363*u^24 - 19755*u^25 - 9649*u^26 + 7900*u^27 + 3922*u^28 - 2179*u^29 - 1088*u^30 + 394*u^31 + 197*u^32 - 42*u^33 - 21*u^34 + 2*u^35 + u^36)",
				"(1 + 2*u - u^2 - u^3)*(1 + u - 7*u^2 - 10*u^3 + 17*u^4 + 32*u^5 - 80*u^6 - 84*u^7 + 266*u^8 + 140*u^9 - 728*u^10 - 288*u^11 + 1430*u^12 + 720*u^13 - 1886*u^14 - 1162*u^15 + 2035*u^16 + 1527*u^17 - 1619*u^18 - 1386*u^19 + 1323*u^20 + 1356*u^21 - 608*u^22 - 806*u^23 + 395*u^24 + 573*u^25 - 93*u^26 - 248*u^27 + 46*u^28 + 129*u^29 + 6*u^30 - 40*u^31 - 5*u^32 + 12*u^33 + 3*u^34 - 2*u^35 - u^36)",
				"(1 + 2*u - u^2 - u^3)*(1 - 7*u + 17*u^2 - 20*u^3 - 51*u^4 + 238*u^5 - 78*u^6 - 464*u^7 + 416*u^8 - 556*u^9 - 18*u^10 + 3674*u^11 - 2562*u^12 - 5478*u^13 + 6374*u^14 - 1134*u^15 - 6461*u^16 + 18355*u^17 - 1011*u^18 - 36852*u^19 + 12199*u^20 + 43442*u^21 - 18546*u^22 - 34866*u^23 + 16363*u^24 + 19755*u^25 - 9649*u^26 - 7900*u^27 + 3922*u^28 + 2179*u^29 - 1088*u^30 - 394*u^31 + 197*u^32 + 42*u^33 - 21*u^34 - 2*u^35 + u^36)",
				"(1 + 2*u - u^2 - u^3)*(1 - 7*u + 17*u^2 - 20*u^3 - 51*u^4 + 238*u^5 - 78*u^6 - 464*u^7 + 416*u^8 - 556*u^9 - 18*u^10 + 3674*u^11 - 2562*u^12 - 5478*u^13 + 6374*u^14 - 1134*u^15 - 6461*u^16 + 18355*u^17 - 1011*u^18 - 36852*u^19 + 12199*u^20 + 43442*u^21 - 18546*u^22 - 34866*u^23 + 16363*u^24 + 19755*u^25 - 9649*u^26 - 7900*u^27 + 3922*u^28 + 2179*u^29 - 1088*u^30 - 394*u^31 + 197*u^32 + 42*u^33 - 21*u^34 - 2*u^35 + u^36)",
				"(1 + 2*u - u^2 - u^3)*(1 - 7*u + 17*u^2 - 20*u^3 - 51*u^4 + 238*u^5 - 78*u^6 - 464*u^7 + 416*u^8 - 556*u^9 - 18*u^10 + 3674*u^11 - 2562*u^12 - 5478*u^13 + 6374*u^14 - 1134*u^15 - 6461*u^16 + 18355*u^17 - 1011*u^18 - 36852*u^19 + 12199*u^20 + 43442*u^21 - 18546*u^22 - 34866*u^23 + 16363*u^24 + 19755*u^25 - 9649*u^26 - 7900*u^27 + 3922*u^28 + 2179*u^29 - 1088*u^30 - 394*u^31 + 197*u^32 + 42*u^33 - 21*u^34 - 2*u^35 + u^36)"
			],
			"RileyPolyC":[
				"(-1 + y)^3*(1 - 1288*y + 16358*y^2 - 102720*y^3 + 433229*y^4 - 1385504*y^5 + 3573036*y^6 - 7701924*y^7 + 14207226*y^8 - 22824212*y^9 + 32403720*y^10 - 41180276*y^11 + 47401908*y^12 - 49968688*y^13 + 48735662*y^14 - 44384994*y^15 + 38025867*y^16 - 30785546*y^17 + 23573990*y^18 - 17035524*y^19 + 11582905*y^20 - 7416896*y^21 + 4520202*y^22 - 2684750*y^23 + 1600691*y^24 - 971050*y^25 + 587692*y^26 - 339942*y^27 + 180040*y^28 - 84500*y^29 + 34323*y^30 - 11819*y^31 + 3371*y^32 - 771*y^33 + 134*y^34 - 16*y^35 + y^36)",
				"(-1 + y)^3*(1 - 1626228*y + 3843902*y^2 + 60209332*y^3 + 133128685*y^4 + 54269056*y^5 - 413733508*y^6 - 1281955716*y^7 - 608438742*y^8 + 2143250412*y^9 + 3531993752*y^10 + 1280949148*y^11 - 1876951260*y^12 - 3958683888*y^13 - 6052201762*y^14 - 8425077138*y^15 - 9190505449*y^16 - 7254939942*y^17 - 3564250118*y^18 - 83572392*y^19 + 1810313153*y^20 + 2035145464*y^21 + 1410493450*y^22 + 729135738*y^23 + 308845359*y^24 + 115823842*y^25 + 39703872*y^26 + 11613886*y^27 + 2442228*y^28 + 200800*y^29 - 74317*y^30 - 34135*y^31 - 6613*y^32 - 575*y^33 + 26*y^34 + 12*y^35 + y^36)",
				"y^3*(64 - 2896*y + 21816*y^2 + 9375*y^3 - 419399*y^4 + 90320*y^5 + 6075840*y^6 - 17601924*y^7 + 23487752*y^8 - 38317776*y^9 + 89612120*y^10 - 90317774*y^11 - 120533230*y^12 + 423965504*y^13 - 334553592*y^14 - 421624070*y^15 + 1415696546*y^16 - 1912395458*y^17 + 1648242588*y^18 - 987349683*y^19 + 420806267*y^20 - 140983764*y^21 + 62853048*y^22 - 49590926*y^23 + 36972062*y^24 - 20330974*y^25 + 8137700*y^26 - 2402807*y^27 + 552695*y^28 - 128834*y^29 + 44720*y^30 - 17971*y^31 + 5789*y^32 - 1339*y^33 + 212*y^34 - 21*y^35 + y^36)",
				"(-1 + y)^3*(-1 + 1288*y - 16358*y^2 + 102720*y^3 - 433229*y^4 + 1385504*y^5 - 3573036*y^6 + 7701924*y^7 - 14207226*y^8 + 22824212*y^9 - 32403720*y^10 + 41180276*y^11 - 47401908*y^12 + 49968688*y^13 - 48735662*y^14 + 44384994*y^15 - 38025867*y^16 + 30785546*y^17 - 23573990*y^18 + 17035524*y^19 - 11582905*y^20 + 7416896*y^21 - 4520202*y^22 + 2684750*y^23 - 1600691*y^24 + 971050*y^25 - 587692*y^26 + 339942*y^27 - 180040*y^28 + 84500*y^29 - 34323*y^30 + 11819*y^31 - 3371*y^32 + 771*y^33 - 134*y^34 + 16*y^35 - y^36)",
				"(-1 + 6*y - 5*y^2 + y^3)*(1 - 15*y + 103*y^2 - 562*y^3 + 2749*y^4 - 10884*y^5 + 37248*y^6 - 114320*y^7 + 325006*y^8 - 852306*y^9 + 1996286*y^10 - 4093736*y^11 + 7300912*y^12 - 11408466*y^13 + 15782560*y^14 - 19527536*y^15 + 21809731*y^16 - 22131115*y^17 + 20556345*y^18 - 17524202*y^19 + 13793905*y^20 - 10025362*y^21 + 6757844*y^22 - 4218456*y^23 + 2443643*y^24 - 1311487*y^25 + 650687*y^26 - 298466*y^27 + 125348*y^28 - 48389*y^29 + 16792*y^30 - 5286*y^31 + 1445*y^32 - 346*y^33 + 67*y^34 - 10*y^35 + y^36)",
				"-(y^3*(64 - 2896*y + 21816*y^2 + 9375*y^3 - 419399*y^4 + 90320*y^5 + 6075840*y^6 - 17601924*y^7 + 23487752*y^8 - 38317776*y^9 + 89612120*y^10 - 90317774*y^11 - 120533230*y^12 + 423965504*y^13 - 334553592*y^14 - 421624070*y^15 + 1415696546*y^16 - 1912395458*y^17 + 1648242588*y^18 - 987349683*y^19 + 420806267*y^20 - 140983764*y^21 + 62853048*y^22 - 49590926*y^23 + 36972062*y^24 - 20330974*y^25 + 8137700*y^26 - 2402807*y^27 + 552695*y^28 - 128834*y^29 + 44720*y^30 - 17971*y^31 + 5789*y^32 - 1339*y^33 + 212*y^34 - 21*y^35 + y^36))",
				"(-1 + 6*y - 5*y^2 + y^3)*(1 - 15*y - 93*y^2 + 1042*y^3 + 3805*y^4 - 60924*y^5 + 207976*y^6 - 17792*y^7 - 1858806*y^8 + 5432326*y^9 - 2716598*y^10 - 23360924*y^11 + 74090292*y^12 - 90003450*y^13 - 45862144*y^14 + 382371744*y^15 - 716230605*y^16 + 579739005*y^17 + 444515861*y^18 - 2283432418*y^19 + 4255599869*y^20 - 5478620262*y^21 + 5472774652*y^22 - 4428307732*y^23 + 2959796263*y^24 - 1648956039*y^25 + 768122927*y^26 - 298887382*y^27 + 96726312*y^28 - 25832441*y^29 + 5626668*y^30 - 982566*y^31 + 134161*y^32 - 13790*y^33 + 1003*y^34 - 46*y^35 + y^36)",
				"(-1 + 6*y - 5*y^2 + y^3)*(1 - 15*y - 93*y^2 + 1042*y^3 + 3805*y^4 - 60924*y^5 + 207976*y^6 - 17792*y^7 - 1858806*y^8 + 5432326*y^9 - 2716598*y^10 - 23360924*y^11 + 74090292*y^12 - 90003450*y^13 - 45862144*y^14 + 382371744*y^15 - 716230605*y^16 + 579739005*y^17 + 444515861*y^18 - 2283432418*y^19 + 4255599869*y^20 - 5478620262*y^21 + 5472774652*y^22 - 4428307732*y^23 + 2959796263*y^24 - 1648956039*y^25 + 768122927*y^26 - 298887382*y^27 + 96726312*y^28 - 25832441*y^29 + 5626668*y^30 - 982566*y^31 + 134161*y^32 - 13790*y^33 + 1003*y^34 - 46*y^35 + y^36)",
				"(1 - 6*y + 5*y^2 - y^3)*(-1 + 15*y - 103*y^2 + 562*y^3 - 2749*y^4 + 10884*y^5 - 37248*y^6 + 114320*y^7 - 325006*y^8 + 852306*y^9 - 1996286*y^10 + 4093736*y^11 - 7300912*y^12 + 11408466*y^13 - 15782560*y^14 + 19527536*y^15 - 21809731*y^16 + 22131115*y^17 - 20556345*y^18 + 17524202*y^19 - 13793905*y^20 + 10025362*y^21 - 6757844*y^22 + 4218456*y^23 - 2443643*y^24 + 1311487*y^25 - 650687*y^26 + 298466*y^27 - 125348*y^28 + 48389*y^29 - 16792*y^30 + 5286*y^31 - 1445*y^32 + 346*y^33 - 67*y^34 + 10*y^35 - y^36)",
				"(1 - 6*y + 5*y^2 - y^3)*(1 - 15*y - 93*y^2 + 1042*y^3 + 3805*y^4 - 60924*y^5 + 207976*y^6 - 17792*y^7 - 1858806*y^8 + 5432326*y^9 - 2716598*y^10 - 23360924*y^11 + 74090292*y^12 - 90003450*y^13 - 45862144*y^14 + 382371744*y^15 - 716230605*y^16 + 579739005*y^17 + 444515861*y^18 - 2283432418*y^19 + 4255599869*y^20 - 5478620262*y^21 + 5472774652*y^22 - 4428307732*y^23 + 2959796263*y^24 - 1648956039*y^25 + 768122927*y^26 - 298887382*y^27 + 96726312*y^28 - 25832441*y^29 + 5626668*y^30 - 982566*y^31 + 134161*y^32 - 13790*y^33 + 1003*y^34 - 46*y^35 + y^36)",
				"(1 - 6*y + 5*y^2 - y^3)*(1 - 15*y - 93*y^2 + 1042*y^3 + 3805*y^4 - 60924*y^5 + 207976*y^6 - 17792*y^7 - 1858806*y^8 + 5432326*y^9 - 2716598*y^10 - 23360924*y^11 + 74090292*y^12 - 90003450*y^13 - 45862144*y^14 + 382371744*y^15 - 716230605*y^16 + 579739005*y^17 + 444515861*y^18 - 2283432418*y^19 + 4255599869*y^20 - 5478620262*y^21 + 5472774652*y^22 - 4428307732*y^23 + 2959796263*y^24 - 1648956039*y^25 + 768122927*y^26 - 298887382*y^27 + 96726312*y^28 - 25832441*y^29 + 5626668*y^30 - 982566*y^31 + 134161*y^32 - 13790*y^33 + 1003*y^34 - 46*y^35 + y^36)",
				"(1 - 6*y + 5*y^2 - y^3)*(1 - 15*y - 93*y^2 + 1042*y^3 + 3805*y^4 - 60924*y^5 + 207976*y^6 - 17792*y^7 - 1858806*y^8 + 5432326*y^9 - 2716598*y^10 - 23360924*y^11 + 74090292*y^12 - 90003450*y^13 - 45862144*y^14 + 382371744*y^15 - 716230605*y^16 + 579739005*y^17 + 444515861*y^18 - 2283432418*y^19 + 4255599869*y^20 - 5478620262*y^21 + 5472774652*y^22 - 4428307732*y^23 + 2959796263*y^24 - 1648956039*y^25 + 768122927*y^26 - 298887382*y^27 + 96726312*y^28 - 25832441*y^29 + 5626668*y^30 - 982566*y^31 + 134161*y^32 - 13790*y^33 + 1003*y^34 - 46*y^35 + y^36)"
			]
		}
	]
}